[
  {
    "title": "පිහිනුම් තටාකයේ විනෝද වූ පුද්ගලයෙක් දියේ ගිලී මරුට",
    "href": "",
    "byline": "අවිස්සාවේල්ල පොලිස් වසමේ පුවක්පිටිය ප්‍රදේශයේ පිහිණුම් තටාකයක ගිලී ඊයේ (04දා) පුද්ගලයෙකු  මියගොස් ඇති බවට අවිස්සාවේල්ල පොලිස් ස්ථානයට ලද පණිවිඩයක් සම්බන්ධයෙන් විමර්ශනයක් ආරම්භ කර ඇත. මරණකරු වයස අවුරුදු 52 ක් වූ මාලඹේ ප්‍රදේශයේ පදිංචිකරුවෙකි.",
    "timestamp": "5 02 2026 09:21:00",
    "url": "https://www.ada.lk/breaking_news/පිහිනුම්-තටාකයේ-විනෝද-වූ-පුද්ගලයෙක්-දියේ-ගිලී-මරුට/11-421099",
    "isoTimestamp": "2026-02-05T10:36:05+05:30",
    "baseUrl": "https://www.ada.lk",
    "checkSum": "a96cee82029200f8ff725b118b8bf5a486842e2bee43fb9dfdc9961b23fd962a"
  },
  {
    "title": "කොරියානු පොප් ප්‍රසංගයකට කොරියානු පොප් කණ්ඩායමක් ලංකාවට එයි",
    "href": "",
    "byline": "ශ්‍රී ලංකාව තුළ ප්‍රථම වරට කොරියානු පොප් සංගීත ප්‍රසංගයක් ( Korean Pop Music ) පැවැත්වීම සදහා දකුණු කොරියාවේ අතිශය ජනප්‍රිය ’’ Sweet - ch ’’ සංගීත කණ්ඩායම 02/04 දින පස්වරුවේ කටුනායක ගුවන් තොටුපොළ ඔස්සේ මෙරටට පැමිණියහ .",
    "timestamp": "5 02 2026 08:32:00",
    "url": "https://www.ada.lk/picture_story/කොරියානු-පොප්-ප්‍රසංගයකට-කොරියානු-පොප්-කණ්ඩායමක්-ලංකාවට-එයි/10-421097",
    "isoTimestamp": "2026-02-05T10:36:05+05:30",
    "baseUrl": "https://www.ada.lk",
    "checkSum": "b6a411e312ef4352ccb45dc9741edb24ac51a96f5fa062e781504f3b50332dd0"
  },
  {
    "title": "දෙව්නි මෝරි සර්වඥ ධාතූන් වහන්සේලා කටුනායකට වඩමවති",
    "href": "",
    "byline": "මෙම සර්වඥ ධාතූන් වහන්සේලා 1960 දශකයේ දී ඉන්දියාවේ ගුජරාට් ප්‍රාන්තයේ , ඓතිහාසික ’’ දෙව්නි මෝරි ’’ කැනීම් භූමියෙන් සොයා ගෙන ඇති අතර , ඒවා මෙතෙක් ඉන්දියාවෙන් පිටතට රැගෙන ගොස් නොතිබුණි .",
    "timestamp": "4 02 2026 18:22:00",
    "url": "https://www.ada.lk/breaking_news/දෙව්නි-මෝරි-සර්වඥ-ධාතූන්-වහන්සේලා-කටුනායකට-වඩමවති/11-421096",
    "isoTimestamp": "2026-02-05T10:36:05+05:30",
    "baseUrl": "https://www.ada.lk",
    "checkSum": "b84fecdce5ddf8db6c37711459fea30e42a42b88634d566f2767c73fcececcae"
  },
  {
    "title": "නව විගණාකාධිපතිනිය වැඩ අරඹයි",
    "href": "",
    "byline": "නව විගණාකාධිපති ලෙස තෙරි පත් වූ සමුදිකා ජයරත්න මහත්මිය අද (05දා) එම ධුරයේ වැඩ භාර ගෙන තිබේ.",
    "timestamp": "5 02 2026 13:03:00",
    "url": "https://www.ada.lk/breaking_news/නව-විගණාකාධිපතිනිය-වැඩ-අරඹයි/11-421104",
    "isoTimestamp": "2026-02-05T13:35:26+05:30",
    "baseUrl": "https://www.ada.lk",
    "checkSum": "a2eaebf0784afcf0665dbbca65fc9fda0e28e28ccbadebd035d900d6b6619434"
  },
  {
    "title": "තායිවානයට ආයුධ සැපයීමේදි විචක්ෂණශීලි වෙන්න යැයි ෂී ට්‍රම්ප්ට කියයි",
    "href": "",
    "byline": "චීන-ඇමරිකානු සබඳතාවලදී ’’වැදගත්ම ගැටලුව’’ ලෙස තායිවානය හැඳින්විය හැකි බව චීන ජනපති ෂී ජින්පින් ඇමෙරිකානු ජනපති ඩොනල්ඩ් ට්‍රම්ප් හා පැවැති දුරකතන සංවාදයකදී පවසා තිබේ. මෙම දුරකතන සංවාදය බදාදා පවත්වා තිබේ.",
    "timestamp": "5 02 2026 11:39:00",
    "url": "https://www.ada.lk/breaking_news/තායිවානයට-ආයුධ-සැපයීමේදි-විචක්ෂණශීලි-වෙන්න-යැයි-ෂී-ට්‍රම්ප්ට-කියයි/11-421101",
    "isoTimestamp": "2026-02-05T13:35:26+05:30",
    "baseUrl": "https://www.ada.lk",
    "checkSum": "d2f0a698e57cc803197c92ee509890b39e1b920576a45ff193e5ae38d003a311"
  },
  {
    "title": "යතුරුපැදි අනතුරකින් පුද්ගලයින් දෙදෙනෙකු ජීවිතක්ෂයට",
    "href": "",
    "byline": "කටාන පොලිස් වසමේ මීගමුව මීරිගම මාර්ගයේ කඳවල ප්‍රදේශයේදී ඊයේ සවස මීගමුව දෙසට ධාවනය වූ යතුරුපැදියක් මාර්ගය හරහා ගමන් කළ පදිකයකුගේ ගැටී අනතුරක් සිදුව ඇත. අනතුරින් යතුරු පැදිකරු, පසුපැදිකරු සහ පදිකයා තුවාල ලබා මීගමුව රෝහලට ඇතුළත් කිරීමෙන් පසු පැදිකරු සහ පදිකයා මියගොස් ඇත. මියගිය පැදිකරු අවුරුදු 19 ක්  සහ පදිකයා අවුරුදු 46  ක් වූ තිබිරිගස්කටුව, කටාන ප්‍රදේශයේ පදිංචිකරුවන් වේ.  මෘත ශරීර මීගමුව රෝහලේ මෘත ශරීරාගාරයේ තැන්පත් කර ඇත. කටාන පොලිසිය වැඩිදුර වි",
    "timestamp": "5 02 2026 10:29:00",
    "url": "https://www.ada.lk/breaking_news/යතුරුපැදි-අනතුරකින්-පුද්ගලයින්-දෙදෙනෙකු-ජීවිතක්ෂයට/11-421100",
    "isoTimestamp": "2026-02-05T13:35:26+05:30",
    "baseUrl": "https://www.ada.lk",
    "checkSum": "ce606af57017421375c88c78827ef9c412982acbc9ffb2163e7c5a202d9f42a5"
  },
  {
    "title": "සහකාර පොලිස් අධිකාරී රොහාන් ඕලුගල ප්‍රතිකාර සඳහා ජාතික රෝහලට",
    "href": "",
    "byline": "සහකාර පොලිස් අධිකාරී රොහාන් ඕලුගල මහතා රෝගී තත්ත්වයක් හේතුවෙන් කොළඹ ජාතික රෝහලේ හදිසි ප්‍රතිකාර ඒකකයට ඇතුළත් කර ඇති බව වාර්ථා වනවා.",
    "timestamp": "5 02 2026 13:33:00",
    "url": "https://www.ada.lk/breaking_news/සහකාර-පොලිස්-අධිකාරී-රොහාන්-ඕලුගල-ප්‍රතිකාර-සඳහා-ජාතික-රෝහලට/11-421106",
    "isoTimestamp": "2026-02-05T16:35:12+05:30",
    "baseUrl": "https://www.ada.lk",
    "checkSum": "de0c19a1f0eb9e3ae6f8946479bce6dc52b7c6c55c3b9d27d17e1b4c10e18f3e"
  },
  {
    "title": "ගල් බෝතලයේ මිල අඩුකරගන්න රෝහිත පෙරට එයි",
    "href": "",
    "byline": "රටේ මත්පැන් භාවිත කරන පිරිසෙන් වැඩි පිරිසක් භාවිත කරන මත්පැන් වර්ගයේ මිල අඩු කරන ලෙස රජයෙන් ඉල්ලන බවට පාර්ලිමේන්තු මන්ත්‍රී රෝහිත අබේගුණවර්ධන පවසයි.",
    "timestamp": "5 02 2026 13:12:00",
    "url": "https://www.ada.lk/breaking_news/ගල්-බෝතලයේ-මිල-අඩුකරගන්න-රෝහිත-පෙරට-එයි/11-421105",
    "isoTimestamp": "2026-02-05T16:35:12+05:30",
    "baseUrl": "https://www.ada.lk",
    "checkSum": "e6dbe846f404cad557da9927f53c2e7685334c14770d1db1b4d3e7793613455e"
  },
  {
    "title": "සිසුන් දෙන්නයි, ගුරුවරු දෙන්නයි, සංවර්ධන නිලධාරින් 4ක් ඉන්න අරුම පුදුම පාසල",
    "href": "",
    "byline": "මොනරාගල අධ්‍යාපන කලාපයේ බඩල්කුඹුර කොට්ඨාසයේ වෙහෙරබැඳිතැන්න කනිෂ්ඨ විද්‍යාලේ ඉගෙනුම ලබන පාසල් ළමුන් දෙදෙනාට ගුරුවරුන් දෙදෙනෙක් සහ සංවර්ධන නිලධාරීන් හතර දෙනෙකු සේවයේ නිරතව සිටී.",
    "timestamp": "5 02 2026 18:48:00",
    "url": "https://www.ada.lk/breaking_news/සිසුන්-දෙන්නයි--ගුරුවරු-දෙන්නයි--සංවර්ධන-නිලධාරින්-4ක්-ඉන්න-අරුම-පුදුම-පාසල/11-421111",
    "isoTimestamp": "2026-02-05T20:35:11+05:30",
    "baseUrl": "https://www.ada.lk",
    "checkSum": "2b68840faa4357610ab435840795c0b1e4006383bed487c99ec48b527458be28"
  },
  {
    "title": "වසර 03කදී විදුලි බල සියයට 30කින් අඩු කරනවා",
    "href": "",
    "byline": "විදුලි ඒකකයක් සඳහා යන වියදමේ සාමාන්‍යය රුපියල් 37 සිට රුපියල් 29 දක්වා අඩු කර ඇති බවත්ති රජය පොරොන්දු වූ පරිදි වසර තුලකදී විදුලි බිල සියයට 30කින් අඩු කරන බවත් බලශක්ති අමාත්‍ය කුමාර ජයකොඩි මහතා අද (05) පාර්ලිමේන්තුවේදී පැවැසීය.",
    "timestamp": "5 02 2026 17:13:00",
    "url": "https://www.ada.lk/breaking_news/වසර-03කදී-විදුලි-බල-සියයට-30කින්-අඩු-කරනවා/11-421110",
    "isoTimestamp": "2026-02-05T20:35:11+05:30",
    "baseUrl": "https://www.ada.lk",
    "checkSum": "d08de33dd47a76bac61dad53790709bbdf99e28738ddc5b8124a25b70c7095a6"
  },
  {
    "title": "ළමුන්ට සමාජ මාධ්‍ය තහනම් කිරීම ගැන ඉන්දියාවේත් කථාවක්",
    "href": "",
    "byline": "වයස අවුරුදු 16 ට අඩු ළමුන් සඳහා සමාජ මාධ්‍ය තහනම් කිරීම පිළිබඳ විවාදයක් ඉන්දියාවේ ආරම්භ වී ඇති අතර,ප්‍රාන්ත කිහිපයක අමාත්‍යවරුන් පවසන්නේ ඕස්ට්‍රේලියාවේ මෑතකදී ක්‍රියාත්මක වූ නීතිය අධ්‍යයනය කරන බවයි.",
    "timestamp": "5 02 2026 16:17:00",
    "url": "https://www.ada.lk/breaking_news/ළමුන්ට-සමාජ-මාධ්‍ය-තහනම්-කිරීම-ගැන-ඉන්දියාවේත්-කථාවක්/11-421107",
    "isoTimestamp": "2026-02-05T20:35:11+05:30",
    "baseUrl": "https://www.ada.lk",
    "checkSum": "b7e00c2a3344530511c19aef2d08a5efa77e498c986f167576542b1da7feefc6"
  },
  {
    "title": "රණවිරුවා කියන්න ජනාධිපතිටයි ආණ්ඩුවටයි කොන්දක් නෑ",
    "href": "",
    "byline": "’’අපි දෙමළ ජනතාව එක්ක යුද්ධ කරේ නෑ.ලෝකයේ කාටවත් පරාජය කරන්න බෑ කියපු ත්‍රස්තවාදය තමයි අපේ ත්‍රිවිධ හමුදාව පොලිසිය සිවිල් ආරක්ෂක බලකාය පරාජය කළේ.අපේ රටේ නිදහස් දිනයේ රටේ රාජ්‍ය නායකයාට ඒක අභිමානයෙන් කියන්න කොන්දක් නෑ. ආණ්ඩුවට රාජ්‍ය නායකයට ඒක පිළිගන්න හයියක් නෑ ආත්ම ශක්තියක් නෑ’’",
    "timestamp": "5 02 2026 15:31:00",
    "url": "https://www.ada.lk/breaking_news/රණවිරුවා-කියන්න-ජනාධිපතිටයි-ආණ්ඩුවටයි-කොන්දක්-නෑ/11-421108",
    "isoTimestamp": "2026-02-05T20:35:11+05:30",
    "baseUrl": "https://www.ada.lk",
    "checkSum": "b62f607eb6da314a48b3d584fdaa54cbd78c6d0873ea3f25b7707bcc4cb4a5bd"
  },
  {
    "title": "බූස්ස අධි ආරක්ෂිත බන්ධනාගාරයේ නියාමක හෙරොයින් සමග අල්ලයි",
    "href": "",
    "byline": "ගාල්ල බූස්ස අධි ආරක්ෂිත බන්ධනාගාරයේ  හෙරොයින් සඟවා සිටි නියාමකවරයෙකු අද (5) බන්ධනාගාර අධිකාරිවරයාගේ බාරයට ගෙන ඇත.",
    "timestamp": "5 02 2026 14:37:00",
    "url": "https://www.ada.lk/breaking_news/බූස්ස-අධි-ආරක්ෂිත-බන්ධනාගාරයේ-නියාමක-හෙරොයින්-සමග-අල්ලයි/11-421109",
    "isoTimestamp": "2026-02-05T20:35:11+05:30",
    "baseUrl": "https://www.ada.lk",
    "checkSum": "dc7e404e133083e9d1ccf8169de739ffdb8f9e34e121cf197bf7d16b2880b2c6"
  }
]
