[
  {
    "title": "සෝමවංශ අමරසිංහ 09 වැනි ගුණ සැමරුම",
    "href": "/articles/OrWsPD6c2S140p82sVy6",
    "byline": "",
    "timestamp": "4 hours ago",
    "url": "https://www.aruna.lk/articles/OrWsPD6c2S140p82sVy6",
    "isoTimestamp": "2025-06-16T02:26:29+05:30",
    "baseUrl": "https://www.aruna.lk",
    "checkSum": "f69b23ba31ceb7df151b301282f131da876ee844f2dba8b3057560e5928ba8e6"
  },
  {
    "title": "ප්‍රදේශ කිහිපයකට අදත් වැසි",
    "href": "/articles/OPvKdQ2IkMdhG5nJjn1s",
    "byline": "",
    "timestamp": "35 minutes ago",
    "url": "https://www.aruna.lk/articles/OPvKdQ2IkMdhG5nJjn1s",
    "isoTimestamp": "2025-06-16T06:55:32+05:30",
    "baseUrl": "https://www.aruna.lk",
    "checkSum": "de8b2c36e272fdeac72ad088c53a1f01ddf16b0ec4f9b0ec37aaa2971462b58d"
  },
  {
    "title": "කොළඹ මහ නගර සභාවේ මංගල රැස්වීම අද",
    "href": "/articles/7j0EXeOpBVFV0XR3Up4N",
    "byline": "",
    "timestamp": "an hour ago",
    "url": "https://www.aruna.lk/articles/7j0EXeOpBVFV0XR3Up4N",
    "isoTimestamp": "2025-06-16T07:30:32+05:30",
    "baseUrl": "https://www.aruna.lk",
    "checkSum": "72547b8c5696af84b847a1d03170c8f895c914f8f7989bd94d6b345b4eaaf1fe"
  },
  {
    "title": "මොනරා දඬු ලේනා ආරක්ෂිත ලැයිස්තුවෙන් ඉවතට",
    "href": "/articles/PzBwxt0fzm025Xfa7hGD",
    "byline": "",
    "timestamp": "an hour ago",
    "url": "https://www.aruna.lk/articles/PzBwxt0fzm025Xfa7hGD",
    "isoTimestamp": "2025-06-16T07:30:32+05:30",
    "baseUrl": "https://www.aruna.lk",
    "checkSum": "ae5ced0e214b501f0354528df13d1a143aad7c782e0cb27da8b23f094c25d709"
  },
  {
    "title": "ඌරුවරිගයේ වන්නිලා ඇත්තන්ගේ 78වැනි ජන්ම දිනයට පින්කමක්",
    "href": "/articles/fjL9dmCxvtJT8Oe9eMT0",
    "byline": "",
    "timestamp": "2 hours ago",
    "url": "https://www.aruna.lk/articles/fjL9dmCxvtJT8Oe9eMT0",
    "isoTimestamp": "2025-06-16T07:28:32+05:30",
    "baseUrl": "https://www.aruna.lk",
    "checkSum": "5ddefd4eb2c84927e09f3fd37985040ecfbc7002cfd9e1c48637e8f1ff497bca"
  },
  {
    "title": "ඊශ්‍රායලයට ඇතුළුවීමට හා පිටවීමට හැකි ආකාරය ගැන දැනුම්දීමක්",
    "href": "/articles/kAHIYmKeDFg6vFRmkcVu",
    "byline": "",
    "timestamp": "8 hours ago",
    "url": "https://www.aruna.lk/articles/kAHIYmKeDFg6vFRmkcVu",
    "isoTimestamp": "2025-06-16T07:22:32+05:30",
    "baseUrl": "https://www.aruna.lk",
    "checkSum": "cd1094ed791cf62d693f18842a1496662ceb34004b8f05e3fffe8ca5bd240b43"
  },
  {
    "title": "2009ට පෙර ලබා ගත් රියදුරු බලපත්‍ර ගැන නිවේදනයක්",
    "href": "/articles/L0MFokE1e0dk9zr2Rqvh",
    "byline": "",
    "timestamp": "an hour ago",
    "url": "https://www.aruna.lk/articles/L0MFokE1e0dk9zr2Rqvh",
    "isoTimestamp": "2025-06-16T19:12:06+05:30",
    "baseUrl": "https://www.aruna.lk",
    "checkSum": "164cfdb934b237046bb24616a153e4b31cc5ce1727c7d7966477d16bca2a2133"
  },
  {
    "title": "ප්‍රදේශ කිහිපයකට නායයෑම් අනතුරු ඇඟවීම් නිකුත් කෙරේ",
    "href": "/articles/KOpemWPeizb1tn9xmDHA",
    "byline": "",
    "timestamp": "2 hours ago",
    "url": "https://www.aruna.lk/articles/KOpemWPeizb1tn9xmDHA",
    "isoTimestamp": "2025-06-16T19:10:06+05:30",
    "baseUrl": "https://www.aruna.lk",
    "checkSum": "3b3de0a35fd84a6e3b191030991717f9831d38044c280db493b8d7c9802f3980"
  },
  {
    "title": "අපරාධ සහ මූල්‍ය වංචාවන්ට සම්බන්ධ 88කගේ වත්කම් තහනම් කෙරේ",
    "href": "/articles/JEyKLhuvI8Hjs49gXwBu",
    "byline": "",
    "timestamp": "2 hours ago",
    "url": "https://www.aruna.lk/articles/JEyKLhuvI8Hjs49gXwBu",
    "isoTimestamp": "2025-06-16T19:10:06+05:30",
    "baseUrl": "https://www.aruna.lk",
    "checkSum": "c2d8ab12b77be7f42d11294ed90d9b310f0b0c8dcbede8bcd5417914fb52abec"
  },
  {
    "title": "බොරතෙල් මිල තවත් ඉහළ යයි",
    "href": "/articles/ee6Zt1rhlsXjhWK8iUqY",
    "byline": "",
    "timestamp": "2 hours ago",
    "url": "https://www.aruna.lk/articles/ee6Zt1rhlsXjhWK8iUqY",
    "isoTimestamp": "2025-06-16T19:10:06+05:30",
    "baseUrl": "https://www.aruna.lk",
    "checkSum": "67fb061086c88993dc4a0d8e7c08073ebb411426f7bcb20d9723270aae580d1a"
  },
  {
    "title": "හර්ෂ ඉලුක්පිටියට එරෙහි පැමිණිල්ල විභාගයට",
    "href": "/articles/sZdF3A954GSg1SZqmHLP",
    "byline": "",
    "timestamp": "3 hours ago",
    "url": "https://www.aruna.lk/articles/sZdF3A954GSg1SZqmHLP",
    "isoTimestamp": "2025-06-16T19:09:06+05:30",
    "baseUrl": "https://www.aruna.lk",
    "checkSum": "7e4e3e53c43e5a99223fc2f8ea3a796dd66ead51650f83a078b40bbf504d4516"
  },
  {
    "title": "වරායේ කළමනාකාර අධ්‍යක්ෂක ඉවත් කිරීමට එරෙහි නඩුව කල්යයි",
    "href": "/articles/4qmAzAGA1M3bu2XNKniR",
    "byline": "",
    "timestamp": "3 hours ago",
    "url": "https://www.aruna.lk/articles/4qmAzAGA1M3bu2XNKniR",
    "isoTimestamp": "2025-06-16T19:09:06+05:30",
    "baseUrl": "https://www.aruna.lk",
    "checkSum": "70467bc9476b42fd5011a2cd61f2c03c8890760037846a67b2c41d2e01cffad7"
  },
  {
    "title": "එයාර් ඉන්දියා ගුවන්යානයක් තාක්ෂණික දෝෂයක් නිසා නැවත හරවයි",
    "href": "/articles/iB7TFrwyqMV43zFcat6S",
    "byline": "",
    "timestamp": "3 hours ago",
    "url": "https://www.aruna.lk/articles/iB7TFrwyqMV43zFcat6S",
    "isoTimestamp": "2025-06-16T19:09:06+05:30",
    "baseUrl": "https://www.aruna.lk",
    "checkSum": "567ae948df4cb27caf0101c9c9aa8f74cb5a9a8f5fc9b606741c00e1d1cc424f"
  },
  {
    "title": "බීමත් රියැදුරා නිසා දිවි අහිමි වූ සහෝදරියන්",
    "href": "/articles/lxmrthO8zVTvJdotEpz0",
    "byline": "",
    "timestamp": "3 hours ago",
    "url": "https://www.aruna.lk/articles/lxmrthO8zVTvJdotEpz0",
    "isoTimestamp": "2025-06-16T19:09:06+05:30",
    "baseUrl": "https://www.aruna.lk",
    "checkSum": "fefebfd3ef58f48642d53bc3ea229086c883baded86e5d9c1af5d68435a32a6d"
  },
  {
    "title": "උසස් පෙළ විශිෂ්ටයින්ට ජනපති අරමුදලින් ශිෂ්‍යත්ව",
    "href": "/articles/cYV5D46zaSFGT8QPtFHX",
    "byline": "",
    "timestamp": "4 hours ago",
    "url": "https://www.aruna.lk/articles/cYV5D46zaSFGT8QPtFHX",
    "isoTimestamp": "2025-06-16T19:08:06+05:30",
    "baseUrl": "https://www.aruna.lk",
    "checkSum": "a00c5f27d2e68fd400c70b43f7bfb131653b745adeee0604cc2230c30a9f71a1"
  },
  {
    "title": "දඹුල්ල ප්‍රා සභාවේ සජබ සභිකයින්ගේ සාමාජිකත්වය අත්හිටුවයි",
    "href": "/articles/lXqy15vQgDZOcnAicFOo",
    "byline": "",
    "timestamp": "4 hours ago",
    "url": "https://www.aruna.lk/articles/lXqy15vQgDZOcnAicFOo",
    "isoTimestamp": "2025-06-16T19:08:06+05:30",
    "baseUrl": "https://www.aruna.lk",
    "checkSum": "1af9965fc4764909e04f87ab1f3cbb26e021f3dad3f19b1d65d3e51ed95c2efc"
  },
  {
    "title": "වෙන්නප්පුවේ මුරකරු ඝාතනයේ සුලමුල හෙළිවෙයි",
    "href": "/articles/6o7UUQ1JTYqitHJcwCxz",
    "byline": "",
    "timestamp": "4 hours ago",
    "url": "https://www.aruna.lk/articles/6o7UUQ1JTYqitHJcwCxz",
    "isoTimestamp": "2025-06-16T19:08:06+05:30",
    "baseUrl": "https://www.aruna.lk",
    "checkSum": "6a0ce42da2dc486f83bbee9bc8e9595acae9a10312a6c9721234ad489ef7cba3"
  },
  {
    "title": "ඉන්දු-ලංකා අවබෝධතා ගිවිසුම්වලට එරෙහි පෙත්සම් සලකාබැලීම අගෝ.4",
    "href": "/articles/iNYuWoEZJJPxiuGZOrOG",
    "byline": "",
    "timestamp": "4 hours ago",
    "url": "https://www.aruna.lk/articles/iNYuWoEZJJPxiuGZOrOG",
    "isoTimestamp": "2025-06-16T19:08:06+05:30",
    "baseUrl": "https://www.aruna.lk",
    "checkSum": "1bb006a436982f7e9de73c0e0fca7a378c0cddeedacb224ad8c21fa2b1ec9cc5"
  },
  {
    "title": "2050 දී මෙරට හයෙන් එකක් 65 ට වැඩි වැඩිහිටියෝ",
    "href": "/articles/86MeCxaLol6b1X58gT6i",
    "byline": "",
    "timestamp": "5 hours ago",
    "url": "https://www.aruna.lk/articles/86MeCxaLol6b1X58gT6i",
    "isoTimestamp": "2025-06-16T19:07:06+05:30",
    "baseUrl": "https://www.aruna.lk",
    "checkSum": "3f241d8b4ed11edebe0fc09228cddf10b16a38f4040865a88cac84a453a1ff72"
  },
  {
    "title": "නිවසක ස්වයංක්‍රීය ගේට්ටුවට හසුවී මෙහෙකරු ජීවිතක්ෂයට",
    "href": "/articles/Athvot14IRQdQIeyQHFe",
    "byline": "",
    "timestamp": "5 hours ago",
    "url": "https://www.aruna.lk/articles/Athvot14IRQdQIeyQHFe",
    "isoTimestamp": "2025-06-16T19:07:06+05:30",
    "baseUrl": "https://www.aruna.lk",
    "checkSum": "3adde287065145409972d09119af4bcbad36a9e870265a728c1b7f99e7cfafd8"
  },
  {
    "title": "අධික වැසි හේතුවෙන් වටවල අගරවත්ත මාර්ගය නායයාමේ අවදානමක",
    "href": "/articles/3UdI3ltdDHCjVU6MpUv8",
    "byline": "",
    "timestamp": "6 hours ago",
    "url": "https://www.aruna.lk/articles/3UdI3ltdDHCjVU6MpUv8",
    "isoTimestamp": "2025-06-16T19:06:06+05:30",
    "baseUrl": "https://www.aruna.lk",
    "checkSum": "6f525417d26b269bc886e197ec4bda18f1cf102113470ea3c79e2446804c03c7"
  },
  {
    "title": "තවත් මහනගර සභාවක සහ ප්‍රාදේශීය සභා දෙකක බලය ජාතික ජන බලවේගයට",
    "href": "/articles/eFQoNNzWQz2U8WPDQsgH",
    "byline": "",
    "timestamp": "6 hours ago",
    "url": "https://www.aruna.lk/articles/eFQoNNzWQz2U8WPDQsgH",
    "isoTimestamp": "2025-06-16T19:06:06+05:30",
    "baseUrl": "https://www.aruna.lk",
    "checkSum": "88a9140a734e6e810b6945c51c0c63f29dbfd93a7fa0bfbc2b1315fac208bdbd"
  },
  {
    "title": "මෙය අවසාන IMF වැඩසටහන බවට පත්කර ගැනීම අපේක්ෂාවයි",
    "href": "/articles/s7eYg5V7iYlRrnmg3zGa",
    "byline": "",
    "timestamp": "7 hours ago",
    "url": "https://www.aruna.lk/articles/s7eYg5V7iYlRrnmg3zGa",
    "isoTimestamp": "2025-06-16T19:05:06+05:30",
    "baseUrl": "https://www.aruna.lk",
    "checkSum": "cdde93fff03ca2b96e489c91f974c7a16dd5dc4a1c60dd7f354894cb5842d1c2"
  },
  {
    "title": "උඩරට මාර්ගයේ දුම්රිය ධාවනයට බාධා",
    "href": "/articles/Q5NSMc7RzPzktJJjYTwv",
    "byline": "",
    "timestamp": "7 hours ago",
    "url": "https://www.aruna.lk/articles/Q5NSMc7RzPzktJJjYTwv",
    "isoTimestamp": "2025-06-16T19:05:06+05:30",
    "baseUrl": "https://www.aruna.lk",
    "checkSum": "6365b20017577dd41fe75ff7886cc7f4bf28febfac5b8aec9ce3c5ed4443deac"
  },
  {
    "title": "කොළඹ නගරාධිපති ධූරය මාලිමාවට",
    "href": "/articles/AD71Yd5uH46uHNP9wYY8",
    "byline": "",
    "timestamp": "8 hours ago",
    "url": "https://www.aruna.lk/articles/AD71Yd5uH46uHNP9wYY8",
    "isoTimestamp": "2025-06-16T19:04:06+05:30",
    "baseUrl": "https://www.aruna.lk",
    "checkSum": "7b0a84775be46ae78936a4a227ec94c035b12b577d1c856b41fea2ed28b7e6e8"
  },
  {
    "title": "කොළඹ නගරාධිපති තෝරාපත් කර ගැනී‌මේ රහස් ඡන්දය ඇරඹේ",
    "href": "/articles/BqfYb9aD9ynUYLIKRTUX",
    "byline": "",
    "timestamp": "9 hours ago",
    "url": "https://www.aruna.lk/articles/BqfYb9aD9ynUYLIKRTUX",
    "isoTimestamp": "2025-06-16T19:03:06+05:30",
    "baseUrl": "https://www.aruna.lk",
    "checkSum": "04f3355c4a2607ab7e771470d373837ad62803cc3e2ba3519bd30158919a9fa5"
  },
  {
    "title": "කොළඹ මහ නගර සභාවේ මංගල රැස්වීම ඇරඹෙයි",
    "href": "/articles/tEf5LlxL1OTpjaypHoEa",
    "byline": "",
    "timestamp": "9 hours ago",
    "url": "https://www.aruna.lk/articles/tEf5LlxL1OTpjaypHoEa",
    "isoTimestamp": "2025-06-16T19:03:06+05:30",
    "baseUrl": "https://www.aruna.lk",
    "checkSum": "be359467fa141867924c7a7484eaa418192c2726d01d0188846d34aa715d6910"
  },
  {
    "title": "ඉරාන මිසයිල ප්‍රහාරයකින් ශ්‍රී ලාංකික තරුණයෙකුට තුවාල",
    "href": "/articles/dbj9edgtRHYWDfr5aGak",
    "byline": "",
    "timestamp": "10 hours ago",
    "url": "https://www.aruna.lk/articles/dbj9edgtRHYWDfr5aGak",
    "isoTimestamp": "2025-06-16T19:02:06+05:30",
    "baseUrl": "https://www.aruna.lk",
    "checkSum": "8d65a8983cc37982c5f402a089d27b52f31d7764a9d42cb9035d9190f72b0b12"
  },
  {
    "title": "කොළඹ පුරපති සටනේ සර්වජන බලවේගයේ සහාය විපක්ෂයට",
    "href": "/articles/FTlInx78M6tqDn2ChCMk",
    "byline": "",
    "timestamp": "10 hours ago",
    "url": "https://www.aruna.lk/articles/FTlInx78M6tqDn2ChCMk",
    "isoTimestamp": "2025-06-16T19:02:06+05:30",
    "baseUrl": "https://www.aruna.lk",
    "checkSum": "975a8b6b549ca86dccb116d6da11fe4a3488fc8c48e6aa22903f18d0f9fa1bd3"
  },
  {
    "title": "අධිකරණ අමාත්‍යාංශ ඉහළ නිලධාරිනියකගෙන් CIDයට ප්‍රකාශයක්",
    "href": "/articles/gCMy5g9hYtKABzo8hsf5",
    "byline": "",
    "timestamp": "10 hours ago",
    "url": "https://www.aruna.lk/articles/gCMy5g9hYtKABzo8hsf5",
    "isoTimestamp": "2025-06-16T19:02:06+05:30",
    "baseUrl": "https://www.aruna.lk",
    "checkSum": "38d0b313432ff7e0f9cf3f5d82d3aaab02dcce87ef1037450fd845cf6a36c400"
  },
  {
    "title": "ඝාතනයකට ආධාර අනුබල දුන් සැකකරුවෙක් අත්අඩංගුවට",
    "href": "/articles/m9GnvEEzjyMHLWIq6nSv",
    "byline": "",
    "timestamp": "10 hours ago",
    "url": "https://www.aruna.lk/articles/m9GnvEEzjyMHLWIq6nSv",
    "isoTimestamp": "2025-06-16T19:02:06+05:30",
    "baseUrl": "https://www.aruna.lk",
    "checkSum": "b2853a69bda473cd32773a2f30edb01e53d71cc668ce3d309d6860766bc647db"
  },
  {
    "title": "බදු ශක්ති වැඩමුළුව රාජ්‍ය ආයතන 3ක් මග හරී",
    "href": "/articles/G9TdIDvsfmdbWSHynGD8",
    "byline": "",
    "timestamp": "11 hours ago",
    "url": "https://www.aruna.lk/articles/G9TdIDvsfmdbWSHynGD8",
    "isoTimestamp": "2025-06-16T19:01:06+05:30",
    "baseUrl": "https://www.aruna.lk",
    "checkSum": "578cf4d73753552b668b1a234ae439ec5fbb756cf71b47c383ba4d2bbe8f0102"
  },
  {
    "title": "දිස්ත්‍රික්ක 07කට නායයෑමේ අනතුරු ඇඟවීම්",
    "href": "/articles/THt6Coz1uYT6WGRafRRK",
    "byline": "",
    "timestamp": "11 hours ago",
    "url": "https://www.aruna.lk/articles/THt6Coz1uYT6WGRafRRK",
    "isoTimestamp": "2025-06-16T19:01:06+05:30",
    "baseUrl": "https://www.aruna.lk",
    "checkSum": "6df87b96e5f4d39b5f4a0e3e64c69df7d132bb2b7f82e7ad3a778616d6302f7b"
  },
  {
    "title": "ඩෙංගු චක්‍රලේඛයට විරෝධය පා විදුහල්පතිවරු වෙලාවට වැඩ",
    "href": "/articles/dYAkorrEwMMTHWyjK47k",
    "byline": "",
    "timestamp": "11 hours ago",
    "url": "https://www.aruna.lk/articles/dYAkorrEwMMTHWyjK47k",
    "isoTimestamp": "2025-06-16T19:01:06+05:30",
    "baseUrl": "https://www.aruna.lk",
    "checkSum": "73a7ee54131ea710b524c18f394ecda3ca24f23dc47308e53093e96644a0c7b6"
  },
  {
    "title": "යුද ගැටුම් සමඟ බොරතෙල් මිල ඉහළට",
    "href": "/articles/jnqcdY9qLgoSKPr7vssS",
    "byline": "",
    "timestamp": "12 hours ago",
    "url": "https://www.aruna.lk/articles/jnqcdY9qLgoSKPr7vssS",
    "isoTimestamp": "2025-06-16T19:00:06+05:30",
    "baseUrl": "https://www.aruna.lk",
    "checkSum": "20e8c80d1c50f0d6802c0cc7f44877c1e999c8a9d847c65d928d2aaacd664288"
  }
]
