[
  {
    "title": "මම මළා කියපු කතාවට මටම හිනා",
    "href": "",
    "byline": "තමා මියගිය බවට  සමාජ මාධ්‍යයේ පළවූ පෝස්ට් එකෙන් තමා හාස්‍ය රසයක් වින්ද බව ප්‍රජාතන්ත්‍රවාදී වාමාංශික පෙරමුණේ නායක වාසුදේව නානායක්කාර මහතා පැවසීය.",
    "timestamp": "2025 ඔක්තෝබර් මස 15",
    "url": "https://www.lankadeepa.lk/latest_news/%E0%B6%B8%E0%B6%B8-%E0%B6%B8%E0%B7%85-%E0%B6%9A%E0%B6%BA%E0%B6%B4-%E0%B6%9A%E0%B6%AD%E0%B7%80%E0%B6%A7-%E0%B6%B8%E0%B6%A7%E0%B6%B8-%E0%B7%84%E0%B6%B1/1-681429",
    "isoTimestamp": "2025-10-16T06:18:33+05:30",
    "baseUrl": "https://www.lankadeepa.lk/latest-news/1",
    "checkSum": "305d436061313fcbbf4b6c9ee15fa568018e1e77785e388ec5a654e9d3a13629"
  },
  {
    "title": "ඉෂාර සෙව්වන්දි දිවයිනට රැගෙන එයි",
    "href": "",
    "byline": "ප්‍රබල පාතලය ක්‍රියකාවකු වූ ගණේමුල්ල සංජීව ඝාතනයේ ප්‍රධාන සැකකාරියක වන ඉෂාරා සෙව්වන්දි ඇතුළු නේපාලයේදී අත්අඩංගුවට ගත සැකකරුවන් පස් දෙනා නේපාලයේ කත්මණ්ඩු නුවර සිට ශ්‍රී ලන්කන් ගුවන් යානයකින් කටුනායක දිවයිනට අද (15) රාත්‍රී රැගෙන ආ බව පොලිසිය කියයි.",
    "timestamp": "2025 ඔක්තෝබර් මස 15",
    "url": "https://www.lankadeepa.lk/latest_news/%E0%B6%89%E0%B7%82%E0%B6%BB-%E0%B7%83%E0%B7%80%E0%B7%80%E0%B6%B1%E0%B6%AF-%E0%B6%AF%E0%B7%80%E0%B6%BA%E0%B6%B1%E0%B6%A7-%E0%B6%BB%E0%B6%9C%E0%B6%B1-%E0%B6%91%E0%B6%BA/1-681428",
    "isoTimestamp": "2025-10-16T06:18:33+05:30",
    "baseUrl": "https://www.lankadeepa.lk/latest-news/1",
    "checkSum": "0e8d1c29fe29490697d36d9e260a10116db35240157ca96416f7fc87ba1df55b"
  },
  {
    "title": "මනූෂට ඇප",
    "href": "",
    "byline": "ඊශ්‍රායල් රාජ්‍යයේ රැකියා සඳහා ශ්‍රමිකයන් තෝරා ගැනීමේදී සිය අමාත්‍ය ධුරයේ බලය අවභාවිතා කරමින් දේශපාලන හිතවතුන්ට එම අවස්ථාව ලබා දුන්නේ යැයි අල්ලස් කොමිසම මගින්  අත් අඩංගුවට ඉගෙන අධිකරණයට ඉදිරිපත් කළ  හිටපු විදේශ රැකියා හා කම්කරු අමාත්‍ය මලිගස්සේ මනුෂ නලින් නානායක්කාර සැකකරු ඇපමත මුදා හැරීමට කොළඹ ප්‍රධාන මහේස්ත්‍රාත් අසංක එස් බෝදරගම මහතා නියෝග කළේය.",
    "timestamp": "2025 ඔක්තෝබර් මස 15",
    "url": "https://www.lankadeepa.lk/latest_news/%E0%B6%B8%E0%B6%B1%E0%B7%82%E0%B6%A7-%E0%B6%87%E0%B6%B4/1-681427",
    "isoTimestamp": "2025-10-16T06:18:33+05:30",
    "baseUrl": "https://www.lankadeepa.lk/latest-news/1",
    "checkSum": "5429a862418dbf4f56ace0ab88ce6c839393e5c6d3836375822dcbd2497c597e"
  },
  {
    "title": "දූෂණයෙන් ලංකාව 120 තැනට",
    "href": "",
    "byline": "දූෂණයෙන් ලංකාව සිටින්නේ එකසිය විසි වැනි  ස්ථානයේ බව අල්ලස් හෝ  දූෂණ චෝදනා  විමර්ශන  කොමිෂන් සභාවේ අධ්‍යක්ෂ ජනරාල් මහාධිකරණ විනිසුරු රංග දිසානායක මහතා පැවසීය.",
    "timestamp": "2025 ඔක්තෝබර් මස 15",
    "url": "https://www.lankadeepa.lk/latest_news/%E0%B6%AF%E0%B7%82%E0%B6%AB%E0%B6%BA%E0%B6%B1-%E0%B6%BD%E0%B6%9A%E0%B7%80-120-%E0%B6%AD%E0%B6%B1%E0%B6%A7/1-681425",
    "isoTimestamp": "2025-10-16T06:18:33+05:30",
    "baseUrl": "https://www.lankadeepa.lk/latest-news/1",
    "checkSum": "58374df0a477bc1947b415514b5c3e2f97e7a93d2c5b96377935a94fa2d135b6"
  },
  {
    "title": "ගුණරත්න වන්නිනායක ඇප මත මුදා හරියි",
    "href": "",
    "byline": "පොලිස් නිලධාරියකුට බැන තර්ජනය කිරීම  සහ රාජකාරියට බාධා කිරීම සම්බන්ධයෙන් පොලිසිය සොයමින් සිටි  නීතිඥ ගුණරත්න වන්නිනායක මහතා ගල්කිස්ස  අධිකරණයට බාර වීමෙන් පසු  රුපියල් ලක්ෂ 5 බැගින් වූ ශරීර ඇප 2ක් මත මුදාහැරීමට ගල්කිස්ස මහෙස්ත්‍රාත් පසන් අමරසේන මහතා නියෝග කළේය.",
    "timestamp": "2025 ඔක්තෝබර් මස 15",
    "url": "https://www.lankadeepa.lk/latest_news/%E0%B6%9C%E0%B6%AB%E0%B6%BB%E0%B6%AD%E0%B6%B1-%E0%B7%80%E0%B6%B1%E0%B6%B1%E0%B6%B1%E0%B6%BA%E0%B6%9A-%E0%B6%87%E0%B6%B4-%E0%B6%B8%E0%B6%AD-%E0%B6%B8%E0%B6%AF-%E0%B7%84%E0%B6%BB%E0%B6%BA/1-681424",
    "isoTimestamp": "2025-10-16T06:18:33+05:30",
    "baseUrl": "https://www.lankadeepa.lk/latest-news/1",
    "checkSum": "b63b0a516ebb93aa94f5e49b94d1f0254a92760f95707058f1acc91f93838f46"
  },
  {
    "title": "අමාත්‍යාංශ දෙකකට නව ලේකම්වරු",
    "href": "",
    "byline": "වරාය සහ සිවිල් ගුවන් සේවා අමාත්‍යාංශයේ ලේකම්වරයා ලෙස ශ්‍රී ලංකා ක්‍රමසම්පාදන සේවයේ විශේෂ ශ්‍රේණියේ නිලධාරියෙක් වන ඩබ්ලිව්.ඩබ්ලිව්.එස්. මංගල මහතා පත් කර තිබේ.",
    "timestamp": "2025 ඔක්තෝබර් මස 15",
    "url": "https://www.lankadeepa.lk/news/%E0%B6%85%E0%B6%B8%E0%B6%AD%E0%B6%BA%E0%B7%81-%E0%B6%AF%E0%B6%9A%E0%B6%9A%E0%B6%A7-%E0%B6%B1%E0%B7%80-%E0%B6%BD%E0%B6%9A%E0%B6%B8%E0%B7%80%E0%B6%BB/101-681423",
    "isoTimestamp": "2025-10-16T06:18:33+05:30",
    "baseUrl": "https://www.lankadeepa.lk/latest-news/1",
    "checkSum": "12b2f9e998b8bdf0659af1eec28a0f1fd35bc2c1b9416ed445337d7c5be5a023"
  },
  {
    "title": "යුක්තිය පසඳලීමේ ක්‍රියාවලිය දේශපාලනිකරණය වෙලා",
    "href": "",
    "byline": "වර්තමාන ආණ්ඩුව යටතේ යුක්තිය පසඳලීමට අදාළ මූලික විමර්ශන කරන ආයතන දේශපාලනිකරණයක් පිළිබඳව සමාජය තුළ ඉතාම පළල් සංවාදයක් නිර්මාණය වී ඇති බව ශ්‍රී ලංකා පොදුජන පෙරමුණේ හිටපු පාර්ලිමේන්තු මන්ත්‍රී සංජීව එදිරිමාන්න මහතා අද (15) පැවසීය.",
    "timestamp": "2025 ඔක්තෝබර් මස 15",
    "url": "https://www.lankadeepa.lk/news/%E0%B6%BA%E0%B6%9A%E0%B6%AD%E0%B6%BA-%E0%B6%B4%E0%B7%83%E0%B6%B3%E0%B6%BD%E0%B6%B8-%E0%B6%9A%E0%B6%BB%E0%B6%BA%E0%B7%80%E0%B6%BD%E0%B6%BA-%E0%B6%AF%E0%B7%81%E0%B6%B4%E0%B6%BD%E0%B6%B1%E0%B6%9A%E0%B6%BB%E0%B6%AB%E0%B6%BA-%E0%B7%80%E0%B6%BD/101-681422",
    "isoTimestamp": "2025-10-16T06:18:33+05:30",
    "baseUrl": "https://www.lankadeepa.lk/latest-news/1",
    "checkSum": "0a4d6044cc475015ecb45d3fd36705796ad14472056be7b6b61db94a8da4d08f"
  },
  {
    "title": "ලබන පාර්ලිමේන්තු සතියේ වැඩ වෙන හැටි",
    "href": "",
    "byline": "පාර්ලිමේන්තුව ඔක්තෝබර් 21 සිට 24 දක්වා රැස්වීමට නියමිත බව පාර්ලිමේන්තුවේ මහලේකම් කුෂාණි රෝහණදීර මහත්මිය පැවසුවාය.",
    "timestamp": "2025 ඔක්තෝබර් මස 15",
    "url": "https://www.lankadeepa.lk/news/%E0%B6%BD%E0%B6%B6%E0%B6%B1-%E0%B6%B4%E0%B6%BB%E0%B6%BD%E0%B6%B8%E0%B6%B1%E0%B6%AD-%E0%B7%83%E0%B6%AD%E0%B6%BA-%E0%B7%80%E0%B6%A9-%E0%B7%80%E0%B6%B1-%E0%B7%84%E0%B6%A7/101-681421",
    "isoTimestamp": "2025-10-16T06:18:33+05:30",
    "baseUrl": "https://www.lankadeepa.lk/latest-news/1",
    "checkSum": "cd3a3d6d548e5a9bbf7461471d9f3b7d209bb85706296b112f0e3f8b88279eb6"
  },
  {
    "title": "බහු පක්ෂ ක්‍රමය රකින්න ඔක්කොම එක තැනකට එන්න",
    "href": "",
    "byline": "ශ්‍රී ලංකාවේ ප්‍රජාතන්ත්‍රවාදී බහු පක්ෂ ක්‍රමය ආරක්ෂා කිරීම සඳහා සියලු දේශපාලන පක්ෂ එක වේදිකාවකට ගෙන ඒම එක්සත් ජාතික පක්ෂයේ ස්ථාවරය යැයි එක්සත් ජාතික පක්ෂය නිවේදනයක් නිකුත් කරමින් පවසයි.",
    "timestamp": "2025 ඔක්තෝබර් මස 15",
    "url": "https://www.lankadeepa.lk/news/%E0%B6%B6%E0%B7%84-%E0%B6%B4%E0%B6%9A%E0%B7%82-%E0%B6%9A%E0%B6%BB%E0%B6%B8%E0%B6%BA-%E0%B6%BB%E0%B6%9A%E0%B6%B1%E0%B6%B1-%E0%B6%94%E0%B6%9A%E0%B6%9A%E0%B6%B8-%E0%B6%91%E0%B6%9A-%E0%B6%AD%E0%B6%B1%E0%B6%9A%E0%B6%A7-%E0%B6%91%E0%B6%B1%E0%B6%B1/101-681420",
    "isoTimestamp": "2025-10-16T06:18:33+05:30",
    "baseUrl": "https://www.lankadeepa.lk/latest-news/1",
    "checkSum": "3612a67dbfb0c757f8eac83dad877096896df840ebd060d8cbe7b0c9e2c7d6ca"
  },
  {
    "title": "ඉදිරි දිනවල තද වැසි",
    "href": "",
    "byline": "රට තුළ ඉදිරි දින කිහිපයේදී වැසි තත්වයේ වර්ධනයක් බලාපොරොත්තු වන බව කාලගුණ විද්‍යා දෙපාර්තමේන්තුව අද (15) පස්වරුවේ පැවසීය.",
    "timestamp": "2025 ඔක්තෝබර් මස 15",
    "url": "https://www.lankadeepa.lk/news/%E0%B6%89%E0%B6%AF%E0%B6%BB-%E0%B6%AF%E0%B6%B1%E0%B7%80%E0%B6%BD-%E0%B6%AD%E0%B6%AF-%E0%B7%80%E0%B7%83/101-681419",
    "isoTimestamp": "2025-10-16T06:18:33+05:30",
    "baseUrl": "https://www.lankadeepa.lk/latest-news/1",
    "checkSum": "089d6c6472d5e910f3b432f4e9793926d259da9efc5b8328f1212698d2dc5720"
  },
  {
    "title": "මනුෂ අධිකරණයට රැගෙන එයි",
    "href": "",
    "byline": "ඊශ්‍රායල් රාජ්‍යයේ රැකියා සඳහා ශ්‍රමිකයන් තෝරා ගැනීමේදී සිය අමාත්‍ය ධුරයේ බලය අවභාවිතා කරමින් දේශපාලන හිතවතුන්ට එම අවස්ථාව ලබා දුන්නේ යැයි අල්ලස් කොමිසම මගින්  අත්අඩංගුවට ගත්  හිටපු විදේශ රැකියා හා කම්කරු අමාත්‍ය මලිගස්සේ මනුෂ නලින් නානායක්කාර සැකකරු කොළඹ ප්‍රධාන මහේස්ත්‍රාත් අසංක එස් බෝදරගම මහතා හමුවට ඉදිරිපත් කිරීම සඳහා අධිකරණය රැගෙන පැමිණියේය.",
    "timestamp": "2025 ඔක්තෝබර් මස 15",
    "url": "https://www.lankadeepa.lk/news/%E0%B6%B8%E0%B6%B1%E0%B7%82-%E0%B6%85%E0%B6%B0%E0%B6%9A%E0%B6%BB%E0%B6%AB%E0%B6%BA%E0%B6%A7-%E0%B6%BB%E0%B6%9C%E0%B6%B1-%E0%B6%91%E0%B6%BA/101-681418",
    "isoTimestamp": "2025-10-16T06:18:33+05:30",
    "baseUrl": "https://www.lankadeepa.lk/latest-news/1",
    "checkSum": "55cfeb0b1a8ee9081a01e354b5762dbcfac727f059772aa835f0302da6d3b4d1"
  },
  {
    "title": "මනුෂ අත්අඩංගුවට",
    "href": "",
    "byline": "කම්කරු හා විදේශ රැකියා හිටපු අමාත්‍ය මනූෂ නානායක්කාර විසින් අල්ලස් හෝ දුෂණ චෝදනා විමර්ශන කොමිෂන් සභාව විසින් මීට ස්වල්ප මොහොතකට පෙර අත්අඩංගුවට ගනු ලැබීය.",
    "timestamp": "2025 ඔක්තෝබර් මස 15",
    "url": "https://www.lankadeepa.lk/news/%E0%B6%B8%E0%B6%B1%E0%B7%82-%E0%B6%85%E0%B6%AD%E0%B6%85%E0%B6%A9%E0%B6%9C%E0%B7%80%E0%B6%A7/101-681405",
    "isoTimestamp": "2025-10-16T06:18:33+05:30",
    "baseUrl": "https://www.lankadeepa.lk/latest-news/1",
    "checkSum": "88f48d8250e55f8c66b3342bcbfbac9d84c7ae77ea81031b9b2d8bf61cbabf30"
  },
  {
    "title": "අගමැතිනිය හෙට ඉන්දියාවට",
    "href": "",
    "byline": "අග්‍රාමාත්‍ය ආචාර්ය හරිනි අමරසූරිය මෙනවිය දෙදින නිල සංචාරයක් සඳහා  හෙට (16) පෙරවරුවේ ඉන්දියාවට පිටත්ව යාමට නියමිතය.",
    "timestamp": "2025 ඔක්තෝබර් මස 15",
    "url": "https://www.lankadeepa.lk/news/%E0%B6%85%E0%B6%9C%E0%B6%B8%E0%B6%AD%E0%B6%B1%E0%B6%BA-%E0%B7%84%E0%B6%A7-%E0%B6%89%E0%B6%B1%E0%B6%AF%E0%B6%BA%E0%B7%80%E0%B6%A7/101-681404",
    "isoTimestamp": "2025-10-16T06:18:33+05:30",
    "baseUrl": "https://www.lankadeepa.lk/latest-news/1",
    "checkSum": "9e0e9f8aa224cb72c7561927a3be294e1a17bcea9a1336e25312988e256a2302"
  },
  {
    "title": "සයිනොපැක් විජිතට දුන් පොරොන්දුව",
    "href": "",
    "byline": "හම්බන්තොට නව තෙල්  පිරිපහදුව කඩිනමින් ඇරඹීමට   සයිනොපැක් සමාගම අමාත්‍ය විජිත හේරත්ට පොරොන්දු වී ඇත",
    "timestamp": "2025 ඔක්තෝබර් මස 15",
    "url": "https://www.lankadeepa.lk/news/%E0%B7%83%E0%B6%BA%E0%B6%B1%E0%B6%B4%E0%B6%9A-%E0%B7%80%E0%B6%A2%E0%B6%AD%E0%B6%A7-%E0%B6%AF%E0%B6%B1-%E0%B6%B4%E0%B6%BB%E0%B6%B1%E0%B6%AF%E0%B7%80/101-681403",
    "isoTimestamp": "2025-10-16T06:18:33+05:30",
    "baseUrl": "https://www.lankadeepa.lk/latest-news/1",
    "checkSum": "5fe1e3498ffe21e75dc9846a5ae2dd1a1c35e0d16852bbfcb92940ae2b18ecab"
  },
  {
    "title": "ඉෂාරා ගෙන එන්න STF නිලධාරීන් නේපාලයට",
    "href": "",
    "byline": "නේපාලයේදී අත්අඩංගුවට ගත් සංවිධානාත්මක අපරාධකාරියක වන ඉෂාරා සෙව්වන්දි ඇතුළු සැකකරුවන් පස්දෙනා මෙරටට රැගෙන ඒමට සහායවීම සඳහා පොලිස් විශේෂ කාර්ය බළකා නිලධාරීන් දෙදෙනෙකු නේපාලය බලා පිටත්ව ගොස් ඇති බව පොලිස් ආරංචි මාර්ග පවසයි.",
    "timestamp": "2025 ඔක්තෝබර් මස 15",
    "url": "https://www.lankadeepa.lk/news/%E0%B6%89%E0%B7%82%E0%B6%BB-%E0%B6%9C%E0%B6%B1-%E0%B6%91%E0%B6%B1%E0%B6%B1-STF-%E0%B6%B1%E0%B6%BD%E0%B6%B0%E0%B6%BB%E0%B6%B1-%E0%B6%B1%E0%B6%B4%E0%B6%BD%E0%B6%BA%E0%B6%A7/101-681401",
    "isoTimestamp": "2025-10-16T06:18:33+05:30",
    "baseUrl": "https://www.lankadeepa.lk/latest-news/1",
    "checkSum": "5c847a468be8cbe66a42dafb7209df1d4fdd6d99b0917837279212eb0019f3d3"
  },
  {
    "title": "සංචාරක පහසුවට රජයෙන් වැඩ ගොඩක්",
    "href": "",
    "byline": "ඉදිරි සංචාරක සමය ඉලක්ක කර ගනිමින් සංචාරකයන්ගේ පහසුකම් නැංවීමට රජය වැඩසටහන් රැසක් සැලසුම් කර තිබේ.",
    "timestamp": "2025 ඔක්තෝබර් මස 15",
    "url": "https://www.lankadeepa.lk/news/%E0%B7%83%E0%B6%A0%E0%B6%BB%E0%B6%9A-%E0%B6%B4%E0%B7%84%E0%B7%83%E0%B7%80%E0%B6%A7-%E0%B6%BB%E0%B6%A2%E0%B6%BA%E0%B6%B1-%E0%B7%80%E0%B6%A9-%E0%B6%9C%E0%B6%A9%E0%B6%9A/101-681391",
    "isoTimestamp": "2025-10-16T06:18:33+05:30",
    "baseUrl": "https://www.lankadeepa.lk/latest-news/1",
    "checkSum": "36d9bebd09e933585e813a5e83720ba1ab02c7f5639d475d564d9a8abf6f68a8"
  },
  {
    "title": "ලංකාවේ සෞඛ්‍ය සේවය ගැන විදෙස් සුව ඇමතිලාගේ ප්‍රසාදය",
    "href": "",
    "byline": "ලෝක සෞඛ්‍ය සංවිධානයේ දකුණු සහ අග්නිදිග ආසියාතික කලාපයේ 78 වන සමුළුවට මෙරටට පැමිණි විදෙස් සෞඛ්‍ය අමාත්‍යවරුන් සහ මෙරට සෞඛ්‍ය අමාත්‍ය නලින්ද ජයතිස්ස -නියෝජ්‍ය අමාත්‍ය හංසක විජේමුණි මහත්වරුන් අතර සාකච්ඡා කොළඹදී පැවැත්විණි",
    "timestamp": "2025 ඔක්තෝබර් මස 15",
    "url": "https://www.lankadeepa.lk/news/%E0%B6%BD%E0%B6%9A%E0%B7%80-%E0%B7%83%E0%B6%9B%E0%B6%BA-%E0%B7%83%E0%B7%80%E0%B6%BA-%E0%B6%9C%E0%B6%B1-%E0%B7%80%E0%B6%AF%E0%B7%83-%E0%B7%83%E0%B7%80-%E0%B6%87%E0%B6%B8%E0%B6%AD%E0%B6%BD%E0%B6%9C-%E0%B6%B4%E0%B6%BB%E0%B7%83%E0%B6%AF%E0%B6%BA/101-681383",
    "isoTimestamp": "2025-10-16T06:18:33+05:30",
    "baseUrl": "https://www.lankadeepa.lk/latest-news/1",
    "checkSum": "762dee9453cd5a795c55011dfdec7a2841b8355589b8f41526fb967084e5042d"
  },
  {
    "title": "සූදු අධිකාරිය පටන් ගන්න මුදල් සභාවෙන් නියෝගයක්",
    "href": "",
    "byline": "සූදු නියාමන අධිකාරිය ලබන වසරේ ජූනි 30ට පෙර පිහිටුවා මෙහෙයුම් කටයුතු ආරම්භ කිරීමට රජයේ මුදල් පිළිබඳ කාරක සභාව දුන් නිර්දේශය ක්‍රියාත්මක කිරීමට මුදල් අමාත්‍යාංශයේ හා දේශීය ආදායම් දෙපාර්තමේන්තුවේ එකඟතාව පළවිය.",
    "timestamp": "2025 ඔක්තෝබර් මස 15",
    "url": "https://www.lankadeepa.lk/news/%E0%B7%83%E0%B6%AF-%E0%B6%85%E0%B6%B0%E0%B6%9A%E0%B6%BB%E0%B6%BA-%E0%B6%B4%E0%B6%A7%E0%B6%B1-%E0%B6%9C%E0%B6%B1%E0%B6%B1-%E0%B6%B8%E0%B6%AF%E0%B6%BD-%E0%B7%83%E0%B6%B7%E0%B7%80%E0%B6%B1-%E0%B6%B1%E0%B6%BA%E0%B6%9C%E0%B6%BA%E0%B6%9A/101-681378",
    "isoTimestamp": "2025-10-16T06:18:33+05:30",
    "baseUrl": "https://www.lankadeepa.lk/latest-news/1",
    "checkSum": "fe7aedc447fa701a826540e8dd117c2bb366310551e3cc3316c1a39a4fdca2a0"
  },
  {
    "title": "උළුගේතැන්න අධිකරණයෙන් පිටව යයි",
    "href": "",
    "byline": "තරුණයකු අතරුදන් කළැයි කියන සිද්ධියක් සම්බන්ධයෙන් රිමාන්ඩ් ගතව කුරුණෑගල අධිකරණයෙන් ඇප ලැබූ හිටපු නාවික හමුදාපති නිශාන්ත උළුගේතැන්න මහතා ඇප සම්පූර්ණ කිරීමෙන් අනතුරු පොල්ගහවෙළ අධිකරණයෙන් පිටව ගියේය.",
    "timestamp": "2025 ඔක්තෝබර් මස 15",
    "url": "https://www.lankadeepa.lk/news/%E0%B6%8B%E0%B7%85%E0%B6%9C%E0%B6%AD%E0%B6%B1%E0%B6%B1-%E0%B6%85%E0%B6%B0%E0%B6%9A%E0%B6%BB%E0%B6%AB%E0%B6%BA%E0%B6%B1-%E0%B6%B4%E0%B6%A7%E0%B7%80-%E0%B6%BA%E0%B6%BA/101-681369",
    "isoTimestamp": "2025-10-16T06:18:33+05:30",
    "baseUrl": "https://www.lankadeepa.lk/latest-news/1",
    "checkSum": "f2b4e83c1a66914a9ea860c89ccb2c03ea12a6f6ec2189bf475386894ba97914"
  },
  {
    "title": "අගමැතිනිය යළි පැමිණෙයි",
    "href": "",
    "byline": "අග්‍රාමාත්‍ය හරිනි අමරසූරිය මෙනවිය සිය චීන සංචාරය නිමා කර අද(15)  අලුයම කටුනායක ගුවන් තොටුපොළ ඔස්සේ මෙරටට පැමිණි බව ගුවන් තොටුපොළ කාර්යය භාර නිලධාරීවරයා පැවසීය.",
    "timestamp": "2025 ඔක්තෝබර් මස 15",
    "url": "https://www.lankadeepa.lk/news/%E0%B6%85%E0%B6%9C%E0%B6%B8%E0%B6%AD%E0%B6%B1%E0%B6%BA-%E0%B6%BA%E0%B7%85-%E0%B6%B4%E0%B6%B8%E0%B6%AB%E0%B6%BA/101-681367",
    "isoTimestamp": "2025-10-16T06:18:33+05:30",
    "baseUrl": "https://www.lankadeepa.lk/latest-news/1",
    "checkSum": "61ecf78f1214082a99933e69d45b9831ba9e26996cad01beb2a095c16868c500"
  }
]
