[
  {
    "title": "Perpetual Treasuries suspension extended for 6-months: central bank",
    "href": "",
    "byline": "Suspension extended under Registered Stock and Securities Ordinance and Local Treasury Bills Ordinance",
    "timestamp": "July 7, 2025",
    "url": "https://economynext.com/perpetual-treasuries-suspension-extended-for-6-months-central-bank-228969/",
    "isoTimestamp": "2025-07-07T00:00:00+05:30",
    "baseUrl": "https://economynext.com",
    "checkSum": "ebf7e0b024799aad51b6748b2ed07e7c863e823c923f89e16866562e97bc31f2"
  },
  {
    "title": "Sri Lanka tax revenues up 20-pct to May 2025, current, overall deficits sharply down",
    "href": "",
    "byline": "Current spending start to pick up",
    "timestamp": "July 7, 2025",
    "url": "https://economynext.com/sri-lanka-tax-revenues-up-20-pct-to-may-2025-current-overall-deficits-sharply-down-228934/",
    "isoTimestamp": "2025-07-07T00:00:00+05:30",
    "baseUrl": "https://economynext.com",
    "checkSum": "592493e6ff7c521453ce5efeef91f887101d2517760e5ede56a29e642e3d1515"
  },
  {
    "title": "Sri Lanka rupee opens stronger, bond yields steady",
    "href": "",
    "byline": "Stocks opened down",
    "timestamp": "July 7, 2025",
    "url": "https://economynext.com/sri-lanka-rupee-opens-stronger-bond-yields-steady-228956/",
    "isoTimestamp": "2025-07-07T00:00:00+05:30",
    "baseUrl": "https://economynext.com",
    "checkSum": "a36a6dd8db7bc1de035eecb53c49c6a0bafe55401f23b79652b8deafcd5d9b48"
  },
  {
    "title": "Sri Lanka expects Trump tariff letter in next few days : Treasury Secy",
    "href": "",
    "byline": "Country negotiating not to get higher rates than competitors",
    "timestamp": "July 7, 2025",
    "url": "https://economynext.com/sri-lanka-expects-trump-tariff-letter-in-next-few-days-treasury-secy-228940/",
    "isoTimestamp": "2025-07-07T00:00:00+05:30",
    "baseUrl": "https://economynext.com",
    "checkSum": "0c130c2b3bf7364e962299eea9b3181168fd4c20e9b36361ece41dc69edbae42"
  },
  {
    "title": "Work on Sri Lanka Expo 2026 begins, to be biennial event : EDB chief",
    "href": "",
    "byline": "Targeting 1,500 participants",
    "timestamp": "July 7, 2025",
    "url": "https://economynext.com/work-on-sri-lanka-expo-2026-begins-to-be-biennial-event-edb-chief-228995/",
    "isoTimestamp": "2025-07-07T00:00:00+05:30",
    "baseUrl": "https://economynext.com",
    "checkSum": "9b372eccf076a981356aaaf6f8d5539db0ac6297e86a53359fa99c81eaf31901"
  },
  {
    "title": "Trump threatens 10-pct extra tariff on pro-BRICS nations",
    "href": "",
    "byline": "The world awaits letters from Trump which he said would be sent out to countries from Monday",
    "timestamp": "July 7, 2025",
    "url": "https://economynext.com/trump-threatens-10-pct-extra-tariff-on-pro-brics-nations-228993/",
    "isoTimestamp": "2025-07-07T00:00:00+05:30",
    "baseUrl": "https://economynext.com",
    "checkSum": "8a4cb8db3715981da48071c5d7cf94c1ed335de85a55a48109ced2aec7886313"
  },
  {
    "title": "12000 Sri Lankans die from accidents a year, 25-pct fall to their deaths",
    "href": "",
    "byline": "\"Accidents have devastating long-term effects not only on the victims but also on other family members and society",
    "timestamp": "July 7, 2025",
    "url": "https://economynext.com/12000-sri-lankans-die-from-accidents-a-year-25-pct-fall-to-their-deaths-229040/",
    "isoTimestamp": "2025-07-07T00:00:00+05:30",
    "baseUrl": "https://economynext.com",
    "checkSum": "aa243f495b973502db28f7837a0d4ac0aa3d226bf327620464210c77db422916"
  },
  {
    "title": "Sri Lanka's Dockyard plans Rs12.9bn rights issue on Mazagon take-over",
    "href": "",
    "byline": "Mazagon was also ready to take any rights not taken up by other shareholders.",
    "timestamp": "July 7, 2025",
    "url": "https://economynext.com/sri-lankas-dockyard-plans-rs12-9bn-rights-issue-on-mazagon-take-over-229018/",
    "isoTimestamp": "2025-07-07T00:00:00+05:30",
    "baseUrl": "https://economynext.com",
    "checkSum": "469f80dcf4c6170a12228f4a6cda41938a3f14d51e5858fc562cdadeb56f77a5"
  },
  {
    "title": "Sri Lanka, Germany discuss boosting healthcare sector",
    "href": "",
    "byline": "AHK Sri Lanka also presented a position paper addressing key challenges and proposed international best practices",
    "timestamp": "July 7, 2025",
    "url": "https://economynext.com/sri-lanka-germany-discuss-boosting-healthcare-sector-229091/",
    "isoTimestamp": "2025-07-07T00:00:00+05:30",
    "baseUrl": "https://economynext.com",
    "checkSum": "8ba21b72bd1db920f1f3c9aa8e0938b580fc18db25114279d4de2b357cb29510"
  },
  {
    "title": "Sri Lanka hopes for higher revenue from gems, jewelry after VAT refunding",
    "href": "",
    "byline": "Sri Lanka has resumed VAT refunding process from July 4",
    "timestamp": "July 7, 2025",
    "url": "https://economynext.com/sri-lanka-hopes-for-higher-revenue-from-gems-jewelry-after-vat-refunding-229092/",
    "isoTimestamp": "2025-07-07T00:00:00+05:30",
    "baseUrl": "https://economynext.com",
    "checkSum": "294d1f2fa256fad8b053fcf98c03cf08605e435d8c1e64561d8fa80db2a62b44"
  },
  {
    "title": "Sri Lanka rupee closes weaker, bond yields flat",
    "href": "",
    "byline": "Rupee depreciated",
    "timestamp": "July 7, 2025",
    "url": "https://economynext.com/sri-lanka-rupee-closes-weaker-bond-yields-flat-229089/",
    "isoTimestamp": "2025-07-07T00:00:00+05:30",
    "baseUrl": "https://economynext.com",
    "checkSum": "47c8ed692841e2bd7a4b1c9e0b8bcb7a5aa1d31ae97953687ff46c97789e34fb"
  },
  {
    "title": "US tariff uncertainties weigh down Sri Lanka stocks",
    "href": "",
    "byline": "Sri Lanka is yet to receive the letters of the applicable US tariff rate.",
    "timestamp": "July 7, 2025",
    "url": "https://economynext.com/us-tariff-uncertainties-weigh-down-sri-lanka-stocks-229054/",
    "isoTimestamp": "2025-07-07T00:00:00+05:30",
    "baseUrl": "https://economynext.com",
    "checkSum": "2c709e58225eff3d3172fcb783a89525a806e12da4a2226fb5a6cae86dbeb6fe"
  },
  {
    "title": "Trump sends 25-pct tariff letters to Malaysia, Japan, Korea, 40-pct to Laos, Myanmar",
    "href": "",
    "byline": "\"Please understand that the 25% number is far less than what is needed to eliminate the Trade Deficit disparity we have",
    "timestamp": "July 7, 2025",
    "url": "https://economynext.com/trump-sends-25-pct-tariff-letters-to-malaysia-japan-korea-40-pct-to-laos-myanmar-229104/",
    "isoTimestamp": "2025-07-07T00:00:00+05:30",
    "baseUrl": "https://economynext.com",
    "checkSum": "4a667c288736f1065661bbb0c070457abda64f1ddae71e7c82c80144e6ebb723"
  }
]
