[
  {
    "title": "Several spells of showers expected in parts of the island",
    "href": "https://www.adaderana.lk/news.php?nid=104343",
    "byline": "The Meteorology Department says the low-pressure area is in the Southwest Bay of Bengal is likely to move further north-westwards towards the north Tamil Nadu and south Andhra Pradesh coast during the next 2 days.",
    "timestamp": "December 19, 2024  8:16 am",
    "url": "https://www.adaderana.lk/news.php?nid=104343",
    "isoTimestamp": "2024-12-19T10:30:49+05:30",
    "baseUrl": "https://adaderana.lk",
    "checkSum": "6e52ad22648edd986507219b1b0699e42e814c9e8efefc20c4e79a386d6f6b5c"
  },
  {
    "title": "13 die as Indian navy speedboat crashes into passenger ferry off Mumbai",
    "href": "https://www.adaderana.lk/news.php?nid=104344",
    "byline": "An Indian navy speedboat crashed into a ferry carrying over 100 people to a popular tourist destination off Mumbai on Wednesday, killing at least 13, the navy said.",
    "timestamp": "December 19, 2024  8:24 am",
    "url": "https://www.adaderana.lk/news.php?nid=104344",
    "isoTimestamp": "2024-12-19T10:30:49+05:30",
    "baseUrl": "https://adaderana.lk",
    "checkSum": "3d3f34c2b61da51ac49d24a4840d61c780b8b94dfaf1b6abb51ec65fe3e469f0"
  },
  {
    "title": "Sri Lanka’s candidate elected to UNESCO’s Intangible Cultural Heritage Evaluation Body",
    "href": "https://www.adaderana.lk/news.php?nid=104345",
    "byline": "Sri Lanka’s candidate, Dr. Bilinda Devage Nandadeva was elected as an expert to the prestigious Evaluation Body of UNESCO’s 2003 Convention for the Safeguarding of the Intangible Cultural Heritage (ICH) at the 19th Session of the ICH Committee Meeting held in Asunción, Paraguay.",
    "timestamp": "December 19, 2024  8:51 am",
    "url": "https://www.adaderana.lk/news.php?nid=104345",
    "isoTimestamp": "2024-12-19T10:30:49+05:30",
    "baseUrl": "https://adaderana.lk",
    "checkSum": "cb3594d7e3a4588ec899a07e9dfd976c8323a327e77484083a6e32c983263d42"
  },
  {
    "title": "2024 census completed, preliminary report within a month",
    "href": "https://www.adaderana.lk/news.php?nid=104346",
    "byline": "The Department of Census and Statistics has completed the final phase of this year’s Population and Housing Census, with data collection focusing on homeless individuals conducted yesterday (18), between 10:00 p.m. and 12:00 midnight.",
    "timestamp": "December 19, 2024  8:57 am",
    "url": "https://www.adaderana.lk/news.php?nid=104346",
    "isoTimestamp": "2024-12-19T10:30:49+05:30",
    "baseUrl": "https://adaderana.lk",
    "checkSum": "e8fbdf0143e21f24cdd2b975d65d1a97a415fc2252413f06dc96d9298a277a83"
  },
  {
    "title": "Diplomatic steps to reclaim social security funds of Sri Lankan workers in Cyprus",
    "href": "https://www.adaderana.lk/news.php?nid=104347",
    "byline": "National People’s Power (NPP) Member of Parliament Lakshman Nipuna Arachchi has announced that diplomatic measures will be initiated to secure the release of social security funds owed to Sri Lankan workers employed in Cyprus.",
    "timestamp": "December 19, 2024  9:15 am",
    "url": "https://www.adaderana.lk/news.php?nid=104347",
    "isoTimestamp": "2024-12-19T10:30:49+05:30",
    "baseUrl": "https://adaderana.lk",
    "checkSum": "63fca8896e88ba947dcca50e0dfbee3a2e20034f35c296d0e7f3dac38f868349"
  },
  {
    "title": "16 deaths reported in fatal accidents on expressways so far this year",
    "href": "https://www.adaderana.lk/news.php?nid=104337",
    "byline": "Sri Lanka Police says that a total of 16 people have died in 12 fatal accidents on the expressways of Sri Lanka as of December 14 this year.",
    "timestamp": "December 18, 2024  5:36 pm",
    "url": "https://www.adaderana.lk/news.php?nid=104337",
    "isoTimestamp": "2024-12-19T10:30:49+05:30",
    "baseUrl": "https://adaderana.lk",
    "checkSum": "ef1ddd677c03b94f33bbe9159eb09d66673de9e1a4990a21db03e464091ac8ce"
  },
  {
    "title": "2024 O/L exam dates announced",
    "href": "https://www.adaderana.lk/news.php?nid=104338",
    "byline": "The Examinations Department announced that the 2024 (2025) G.C.E. Ordinary Level Examination will be held from the 17th of March to the 26th of March, 2025.",
    "timestamp": "December 18, 2024  6:01 pm",
    "url": "https://www.adaderana.lk/news.php?nid=104338",
    "isoTimestamp": "2024-12-19T10:30:49+05:30",
    "baseUrl": "https://adaderana.lk",
    "checkSum": "2b15ccaf03e73d9163306e4487ca638ed6c69fae7e9bce5ef4d4691b384114ba"
  },
  {
    "title": "Sri Lanka to give free visas to 39 countries - Foreign Minister",
    "href": "https://www.adaderana.lk/news.php?nid=104339",
    "byline": "Sri Lanka’s Minister of Foreign Affairs, Vijitha Herath, has provided an update on the country’s strategic efforts to revitalize its tourism sector, which has faced unprecedented challenges in recent years due to the Easter Sunday attacks, the COVID-19 pandemic, and the economic crisis.",
    "timestamp": "December 18, 2024  7:08 pm",
    "url": "https://www.adaderana.lk/news.php?nid=104339",
    "isoTimestamp": "2024-12-19T10:30:49+05:30",
    "baseUrl": "https://adaderana.lk",
    "checkSum": "8a1b0db0c417bba0c7699eda8675a09ef8fe25044b6ac6c178f2860a421989c8"
  },
  {
    "title": "Passenger boat capsizes off Mumbai coast with more than 80 on board",
    "href": "https://www.adaderana.lk/news.php?nid=104340",
    "byline": "A boat carrying 80 passengers and five crew members capsized off the coast of India’s financial capital Mumbai after a speedboat struck it on Wednesday, local and government officials said.",
    "timestamp": "December 18, 2024  8:41 pm",
    "url": "https://www.adaderana.lk/news.php?nid=104340",
    "isoTimestamp": "2024-12-19T10:30:49+05:30",
    "baseUrl": "https://adaderana.lk",
    "checkSum": "cbfb79b96cef945fd438ff2548e69996246ff38afef8680f3a0f6c990b599b53"
  },
  {
    "title": "16,000 MT of rice imported within two weeks",
    "href": "https://www.adaderana.lk/news.php?nid=104341",
    "byline": "Around 16,000 metric tonnes of rice has been imported to Sri Lanka as of 3:30 p.m. today (18), following the relaxing of import restrictions on rice.",
    "timestamp": "December 18, 2024  9:44 pm",
    "url": "https://www.adaderana.lk/news.php?nid=104341",
    "isoTimestamp": "2024-12-19T10:30:49+05:30",
    "baseUrl": "https://adaderana.lk",
    "checkSum": "4f4e713cddbf40565bbf50e4ecbfdde296136b2c7e095e99382b80e324abb541"
  },
  {
    "title": "President expresses gratitude to China for debt restructuring support and economic assistance",
    "href": "https://www.adaderana.lk/news.php?nid=104342",
    "byline": "President Anura Kumara Dissanayake has expressed his gratitude to the Chinese government for its support during debt restructuring as well as in the face of the economic crisis.",
    "timestamp": "December 18, 2024  10:05 pm",
    "url": "https://www.adaderana.lk/news.php?nid=104342",
    "isoTimestamp": "2024-12-19T10:30:49+05:30",
    "baseUrl": "https://adaderana.lk",
    "checkSum": "71567c4d159c241d93ee471ef83ab3c30e8f74e2a4b41fd1587091d53bacf2b8"
  },
  {
    "title": "Sri Lankan jailed for 37 years for killing wife with axe in front of teenage children",
    "href": "https://www.adaderana.lk/news.php?nid=104348",
    "byline": "A killer has been jailed for 37 years for murdering his wife with an axe in front of their teenage children, in what a judge has described as a brutal and horrific attack.",
    "timestamp": "December 19, 2024  10:32 am",
    "url": "https://www.adaderana.lk/news.php?nid=104348",
    "isoTimestamp": "2024-12-19T16:30:55+05:30",
    "baseUrl": "https://adaderana.lk",
    "checkSum": "c920453f96a133a3491c7d618200f83a01609ca6e15aaed3ee92345ecd0911d7"
  },
  {
    "title": "Sri Lankan man charged for alleged sexual assault on Melbourne flight",
    "href": "https://www.adaderana.lk/news.php?nid=104349",
    "byline": "A Sri Lankan man faced Broadmeadows Magistrates Court today (19 December, 2024) charged with allegedly committing an act of indecency on board an international flight.",
    "timestamp": "December 19, 2024  10:41 am",
    "url": "https://www.adaderana.lk/news.php?nid=104349",
    "isoTimestamp": "2024-12-19T16:30:55+05:30",
    "baseUrl": "https://adaderana.lk",
    "checkSum": "97cf36e1b2f2688e02dcf17b971fbb380c28f001d0d803e31ea50c5cff877e0e"
  },
  {
    "title": "Warrant issued for arrest of Gnanasara Thero",
    "href": "https://www.adaderana.lk/news.php?nid=104350",
    "byline": "The Colombo Magistrate’s Court has issued a warrant for the arrest of the General Secretary of the Bodu Bala Sena (BBS) Organization, Ven. Galagoda Aththe Gnanasara Thero and to produce him before the court.",
    "timestamp": "December 19, 2024  11:01 am",
    "url": "https://www.adaderana.lk/news.php?nid=104350",
    "isoTimestamp": "2024-12-19T16:30:55+05:30",
    "baseUrl": "https://adaderana.lk",
    "checkSum": "82e3af20bab40ed7b897fc4162754a7a08d870ecb46063644264c3b46cc03e10"
  },
  {
    "title": "Police constable injured in attack with broken bottle at Horana",
    "href": "https://www.adaderana.lk/news.php?nid=104351",
    "byline": "A police constable was reportedly attacked with a broken empty liquor bottle at an inn in Horana.",
    "timestamp": "December 19, 2024  11:22 am",
    "url": "https://www.adaderana.lk/news.php?nid=104351",
    "isoTimestamp": "2024-12-19T16:30:55+05:30",
    "baseUrl": "https://adaderana.lk",
    "checkSum": "3e60986fedf29fea9466208c81ccb00d2dea3e500b39b961a361f152c4746357"
  },
  {
    "title": "Cabinet approval to import salt to resolve shortage",
    "href": "https://www.adaderana.lk/news.php?nid=104352",
    "byline": "The Cabinet of Ministers has granted approval for the import of up to 30,000 metric tons of non-iodized salt by the State Trading Corporation to address the ongoing salt shortage in the market.",
    "timestamp": "December 19, 2024  11:35 am",
    "url": "https://www.adaderana.lk/news.php?nid=104352",
    "isoTimestamp": "2024-12-19T16:30:55+05:30",
    "baseUrl": "https://adaderana.lk",
    "checkSum": "b626eef2bc83308bc118dc8ae5f161174deea4c66ee93a2d334f310e7cda3217"
  },
  {
    "title": "Cabinet nod for review of SOEs with non-commercial interests",
    "href": "https://www.adaderana.lk/news.php?nid=104353",
    "byline": "The Cabinet of Ministers has granted approval for the review of State-Owned Enterprises (SOEs) with non-commercial interests.",
    "timestamp": "December 19, 2024  12:51 pm",
    "url": "https://www.adaderana.lk/news.php?nid=104353",
    "isoTimestamp": "2024-12-19T16:30:55+05:30",
    "baseUrl": "https://adaderana.lk",
    "checkSum": "9baad90f09cd3b1fbbcd8643331ba15514d373e73d6528963d94e55536b6f44e"
  },
  {
    "title": "Sri Lanka to import of high-quality dairy cattle from Pakistan",
    "href": "https://www.adaderana.lk/news.php?nid=104354",
    "byline": "The Cabinet of Ministers has granted approval for the import of high-quality genetic dairy cattle from Pakistan in an effort to increase local milk production.",
    "timestamp": "December 19, 2024  1:12 pm",
    "url": "https://www.adaderana.lk/news.php?nid=104354",
    "isoTimestamp": "2024-12-19T16:30:55+05:30",
    "baseUrl": "https://adaderana.lk",
    "checkSum": "6acc6e14f3de3fec0e041805e8b7865b6194792c088bd136a587891911922b89"
  },
  {
    "title": "Sri Lanka Police to receive Rs. 300M Indian grant for new vehicles",
    "href": "https://www.adaderana.lk/news.php?nid=104355",
    "byline": "The Government of India has agreed to provide financial assistance amounting to Sri Lankan Rs. 300 million to address vehicle requirements for the Sri Lanka Police, Cabinet Spokesman Minister Dr. Nalinda Jayatissa announced during the Cabinet press briefing held today (19).",
    "timestamp": "December 19, 2024  2:31 pm",
    "url": "https://www.adaderana.lk/news.php?nid=104355",
    "isoTimestamp": "2024-12-19T16:30:55+05:30",
    "baseUrl": "https://adaderana.lk",
    "checkSum": "d53522ee5689857de02b1e6b0012b81d4da8b47a5738b52b8fff23b8372c045d"
  },
  {
    "title": "ADB extends $150 million line of credit to CEB",
    "href": "https://www.adaderana.lk/news.php?nid=104356",
    "byline": "Asian Development Bank (ADB) and Ceylon Electricity Board (CEB) signed an agreement on Thursday for the ADB to provide a loan of $150 million to the CEB.",
    "timestamp": "December 19, 2024  3:28 pm",
    "url": "https://www.adaderana.lk/news.php?nid=104356",
    "isoTimestamp": "2024-12-19T16:30:55+05:30",
    "baseUrl": "https://adaderana.lk",
    "checkSum": "f946d2d1b0630b1276efbc345e7a0ca3ce36417decf54da613c8b346013bf0d8"
  },
  {
    "title": "Compulsory retirement age of govt doctors extended",
    "href": "https://www.adaderana.lk/news.php?nid=104357",
    "byline": "The Cabinet of Ministers has approved the extension of the compulsory age limit of retirement for government medical officers up to 63 years, with amendments to be made in line with the Pensions Act.",
    "timestamp": "December 19, 2024  3:52 pm",
    "url": "https://www.adaderana.lk/news.php?nid=104357",
    "isoTimestamp": "2024-12-19T16:30:55+05:30",
    "baseUrl": "https://adaderana.lk",
    "checkSum": "eda803296334a08ba2c76805af9b4cf1e4713d7afa7e613fa2eba18214ca245c"
  },
  {
    "title": "Boat carrying over 100 Myanmar refugees reaches Mullaitivu",
    "href": "https://www.adaderana.lk/news.php?nid=104358",
    "byline": "A boat carrying over 100 refugees from Myanmar has reached the shores of the Mullivaikkal area in Mullaitivu, according to Sri Lanka Navy and Police officers in Mullaitivu.",
    "timestamp": "December 19, 2024  4:51 pm",
    "url": "https://www.adaderana.lk/news.php?nid=104358",
    "isoTimestamp": "2024-12-19T22:30:15+05:30",
    "baseUrl": "https://adaderana.lk",
    "checkSum": "d33fcac64148b82240b8646c1359fec24e08c025d5ff01b193a0a22b8adf9150"
  },
  {
    "title": "Sri Lanka must stick with IMF programme in ‘good times and bad’ – Ranil",
    "href": "https://www.adaderana.lk/news.php?nid=104359",
    "byline": "Former President Ranil Wickremesinghe says that criticism pertaining to the country’s economy should be made within the framework of the International Monetary Fund (IMF) agreement.",
    "timestamp": "December 19, 2024  6:06 pm",
    "url": "https://www.adaderana.lk/news.php?nid=104359",
    "isoTimestamp": "2024-12-19T22:30:15+05:30",
    "baseUrl": "https://adaderana.lk",
    "checkSum": "7325e409db224ec1bb98ffabd8e93e204780831ec25fa9f9f225402fe71fd387"
  },
  {
    "title": "Defence Ministry sets deadline to return licensed firearms provided to civilians",
    "href": "https://www.adaderana.lk/news.php?nid=104360",
    "byline": "Sri Lanka’s Ministry of Defence today informed licensees to return all licensed firearms that have not been returned and submitted for inspection, before January 20, 2025, in line with the decision taken to ensure a safe society by minimizing the use and misuse of firearms in the civil society and by implementing proper regulation.",
    "timestamp": "December 19, 2024  7:39 pm",
    "url": "https://www.adaderana.lk/news.php?nid=104360",
    "isoTimestamp": "2024-12-19T22:30:15+05:30",
    "baseUrl": "https://adaderana.lk",
    "checkSum": "73d3040450d17c19a0f17d29e54ab387845ad37bb99f52aad7d1df24734d1b2e"
  },
  {
    "title": "Train derails at Rambukkana causing delays",
    "href": "https://www.adaderana.lk/news.php?nid=104361",
    "byline": "A train traveling from Colombo Fort to Rambukkana has derailed this evening (19) at the Rambukkana railway station after completing its route and while returning to the yard.",
    "timestamp": "December 19, 2024  9:18 pm",
    "url": "https://www.adaderana.lk/news.php?nid=104361",
    "isoTimestamp": "2024-12-19T22:30:15+05:30",
    "baseUrl": "https://adaderana.lk",
    "checkSum": "fb5952dabbf9d8de6d482f778192e24eb6655ef2138b7e18fa185d12bf2dabf2"
  }
]
