[
  {
    "title": "පිටින් ඖෂධ ගන්නමාර්ගෝපදේශ නිකුත් කිරීම ධනාත්මක කරුණක්",
    "href": "/articles/gc5NNqxFcvu7DFoAYIyJ",
    "byline": "",
    "timestamp": "2 hours ago",
    "url": "https://www.aruna.lk/articles/gc5NNqxFcvu7DFoAYIyJ",
    "isoTimestamp": "2025-07-22T07:28:33+05:30",
    "baseUrl": "https://www.aruna.lk",
    "checkSum": "31b379f88813c9077a7eacf9ffaedaf8a18343028de465398378acd8bbbd4b08"
  },
  {
    "title": "මෙම වසරේ මුල් මාස පහේදී අල්ලස් නඩුවලින් ලක්ෂ 14ක ආදායමක්",
    "href": "/articles/kuuXV8z7QK75SUHa9jB5",
    "byline": "",
    "timestamp": "2 hours ago",
    "url": "https://www.aruna.lk/articles/kuuXV8z7QK75SUHa9jB5",
    "isoTimestamp": "2025-07-22T07:28:33+05:30",
    "baseUrl": "https://www.aruna.lk",
    "checkSum": "7132ce80415b45a2c06796662a45e7ffdec84c1abb43ccff42796de290848fdd"
  },
  {
    "title": "තිරිංග පැඩල මිලදී ගැනීමේදී කෝටි 25 ක් පිල්ලි ගහලා",
    "href": "/articles/8bNoEvpZO9ipw49x1XTa",
    "byline": "",
    "timestamp": "2 hours ago",
    "url": "https://www.aruna.lk/articles/8bNoEvpZO9ipw49x1XTa",
    "isoTimestamp": "2025-07-22T07:28:33+05:30",
    "baseUrl": "https://www.aruna.lk",
    "checkSum": "517e1b5de833ba475f4070d7f78be33b6aa2b899523044c09face8e155900506"
  },
  {
    "title": "අලි ඝාතන පරීක්ෂණ CIDයට",
    "href": "/articles/875WuTs3hM5Kx1hbROkQ",
    "byline": "",
    "timestamp": "2 hours ago",
    "url": "https://www.aruna.lk/articles/875WuTs3hM5Kx1hbROkQ",
    "isoTimestamp": "2025-07-22T07:28:33+05:30",
    "baseUrl": "https://www.aruna.lk",
    "checkSum": "5590a19849eb272af5b4065d3b6d7bcd91283fd6443965f5ea73d86949145ff8"
  },
  {
    "title": "බිත්තරේ මිල තවත් බහී",
    "href": "/articles/680HDhTc33DvF98m7Omu",
    "byline": "",
    "timestamp": "2 hours ago",
    "url": "https://www.aruna.lk/articles/680HDhTc33DvF98m7Omu",
    "isoTimestamp": "2025-07-22T07:28:33+05:30",
    "baseUrl": "https://www.aruna.lk",
    "checkSum": "313b5632faf9e91c7b4a83524b2d6f6ec0aa3bddbe8dbe37c399c241fd4f9917"
  },
  {
    "title": "ගමක් එකතු වී රිළවුන් පලවා හැරීමේ මෙහෙයුමක්",
    "href": "/articles/SEfvL94NTSYo0NVJB1c5",
    "byline": "",
    "timestamp": "2 hours ago",
    "url": "https://www.aruna.lk/articles/SEfvL94NTSYo0NVJB1c5",
    "isoTimestamp": "2025-07-22T07:28:33+05:30",
    "baseUrl": "https://www.aruna.lk",
    "checkSum": "03ee98b0f9409582884c396ae6a6d0fad2a668984ae0af23bda83aff5c1b038c"
  },
  {
    "title": "වෙඩිතැබීම් සිද්ධි දෙකකට සම්බන්ධ දෙදෙනෙක් අත්අඩංගුවට",
    "href": "/articles/6umcia3VWv4o5ZDBKiNr",
    "byline": "",
    "timestamp": "9 hours ago",
    "url": "https://www.aruna.lk/articles/6umcia3VWv4o5ZDBKiNr",
    "isoTimestamp": "2025-07-22T07:21:33+05:30",
    "baseUrl": "https://www.aruna.lk",
    "checkSum": "dba5bee53e305d13b6a91b087aaf68ae66fae29e5288805e1b8fa73a44f3cc8e"
  },
  {
    "title": "දේශබන්දු එල්ලවූ චෝදනාවලට වරදකරු වෙයි",
    "href": "/articles/RJA5TlakKsjzlFQGoEt1",
    "byline": "",
    "timestamp": "20 minutes ago",
    "url": "https://www.aruna.lk/articles/RJA5TlakKsjzlFQGoEt1",
    "isoTimestamp": "2025-07-22T10:11:10+05:30",
    "baseUrl": "https://www.aruna.lk",
    "checkSum": "8a499952964df70657bd2ad7088991e602db8a011b3f932047bfa9aeeacb04a0"
  },
  {
    "title": "නව අග විනිසුරු ලෙස ප්‍රීති පද්මන් සූරසේන නිර්දේශ කරයි",
    "href": "/articles/9mBaSYIOss9RN5GaE23E",
    "byline": "",
    "timestamp": "27 minutes ago",
    "url": "https://www.aruna.lk/articles/9mBaSYIOss9RN5GaE23E",
    "isoTimestamp": "2025-07-22T10:04:10+05:30",
    "baseUrl": "https://www.aruna.lk",
    "checkSum": "7c805dd4fa90571570725b5457c2ed25813b5cc10ac90027493cc06045800daa"
  },
  {
    "title": "සීදූව වෙඩි තැබීමේ සිද්ධියට දෙදෙනෙකු අත්අඩංගුවට",
    "href": "/articles/SSDdlZrg0wZQA9PmDxF1",
    "byline": "",
    "timestamp": "34 minutes ago",
    "url": "https://www.aruna.lk/articles/SSDdlZrg0wZQA9PmDxF1",
    "isoTimestamp": "2025-07-22T09:57:10+05:30",
    "baseUrl": "https://www.aruna.lk",
    "checkSum": "af12dc93449aef9d898b601d25455e46eba2058e5c79fddaf47f29d971ab60ce"
  },
  {
    "title": "ගීතා ගෝපිනාත් ජාත්‍යන්තර මූල්‍ය අරමුදලට සමුදෙයි",
    "href": "/articles/jdtOcWvLW8zngcW2ePn1",
    "byline": "",
    "timestamp": "an hour ago",
    "url": "https://www.aruna.lk/articles/jdtOcWvLW8zngcW2ePn1",
    "isoTimestamp": "2025-07-22T10:31:10+05:30",
    "baseUrl": "https://www.aruna.lk",
    "checkSum": "2690dd7bda66e43b78a0cd56c6da998fe9c682d84fbf047d9e1e56e620ad74e0"
  },
  {
    "title": "වෘත්තීය සමිති 28ක විදුලි සේවකයින් අද ලෙඩ නිවාඩු",
    "href": "/articles/DogFT4JZxKpt3eqGCHeq",
    "byline": "",
    "timestamp": "an hour ago",
    "url": "https://www.aruna.lk/articles/DogFT4JZxKpt3eqGCHeq",
    "isoTimestamp": "2025-07-22T10:31:10+05:30",
    "baseUrl": "https://www.aruna.lk",
    "checkSum": "f30369a35e406d370859b2699cd64a67b55c2f8abd203bb75ee4462d41e74581"
  },
  {
    "title": "මාස 7ට ව්‍යාපෘති 57කට BOI අනුමැතිය",
    "href": "/articles/NzBWZslQEgE2mZChvwcn",
    "byline": "",
    "timestamp": "2 hours ago",
    "url": "https://www.aruna.lk/articles/NzBWZslQEgE2mZChvwcn",
    "isoTimestamp": "2025-07-22T10:29:10+05:30",
    "baseUrl": "https://www.aruna.lk",
    "checkSum": "893c3008e90b5e76c896e838acd8e19c85d8d54b4acad64f597b27138c953dd4"
  },
  {
    "title": "ත්‍රිවිල් කොල්ලකෑ සැකකරුවන් පිරිසක් අත්අඩංගුවට",
    "href": "/articles/20GvxYqu1IlOWZukAq9g",
    "byline": "",
    "timestamp": "3 hours ago",
    "url": "https://www.aruna.lk/articles/20GvxYqu1IlOWZukAq9g",
    "isoTimestamp": "2025-07-22T10:28:10+05:30",
    "baseUrl": "https://www.aruna.lk",
    "checkSum": "e8f445a9190b23703fa045c52731afaa31e8ed7e5c3da39efdbbe720bc7edda2"
  },
  {
    "title": "අද කාළගුණය",
    "href": "/articles/JrC4gvbESSVeSrOHZhkA",
    "byline": "",
    "timestamp": "3 hours ago",
    "url": "https://www.aruna.lk/articles/JrC4gvbESSVeSrOHZhkA",
    "isoTimestamp": "2025-07-22T10:28:10+05:30",
    "baseUrl": "https://www.aruna.lk",
    "checkSum": "01f587f2ffd790995559a374c16b3b17cdda119322896df8b44ac6b6644524ad"
  },
  {
    "title": "හිටපු DIG රොහාන් අත්අඩංගුවට ගැනීමේ අවශ්‍යතාවයක් නෑ",
    "href": "/articles/QmCeNzxXYUwa2YOBjsMe",
    "byline": "",
    "timestamp": "19 minutes ago",
    "url": "https://www.aruna.lk/articles/QmCeNzxXYUwa2YOBjsMe",
    "isoTimestamp": "2025-07-22T13:11:53+05:30",
    "baseUrl": "https://www.aruna.lk",
    "checkSum": "0b8ebe29ebf1e0ae864663ed8b9b73e9d7316fa46ebbbf62fadf7935a53a2583"
  },
  {
    "title": "පොලීසියට තවත් නිලධාරීන් 2500ක්",
    "href": "/articles/Zbx3mxuKjfTq6hB176tt",
    "byline": "",
    "timestamp": "an hour ago",
    "url": "https://www.aruna.lk/articles/Zbx3mxuKjfTq6hB176tt",
    "isoTimestamp": "2025-07-22T13:30:53+05:30",
    "baseUrl": "https://www.aruna.lk",
    "checkSum": "11cd51c8826b7d95b3086794d80859260313117e3af2a9aa6d702aa428b2399d"
  },
  {
    "title": "දේශීය ආදායම් නියෝජ්‍ය කොමසාරිස්ට ඇප",
    "href": "/articles/fmomlna8SsK5K24N7T4O",
    "byline": "",
    "timestamp": "an hour ago",
    "url": "https://www.aruna.lk/articles/fmomlna8SsK5K24N7T4O",
    "isoTimestamp": "2025-07-22T13:30:53+05:30",
    "baseUrl": "https://www.aruna.lk",
    "checkSum": "83f3243cd525a93a288842b6c836ded53e9dd4659cc6593a683c10acc769a190"
  },
  {
    "title": "වසර 10ක් තුළ විදෙස් ප්‍රේෂණ ගැන හෙළිදරව්වක්",
    "href": "/articles/3XEjoXWaVBjjB4HhSRM2",
    "byline": "",
    "timestamp": "2 hours ago",
    "url": "https://www.aruna.lk/articles/3XEjoXWaVBjjB4HhSRM2",
    "isoTimestamp": "2025-07-22T13:28:53+05:30",
    "baseUrl": "https://www.aruna.lk",
    "checkSum": "0e16ec58e08ec7deb4abf6d5d75f626fb21dc10eecfce5a53076ccec1e8723bf"
  },
  {
    "title": "හෂීෂ් මත්ද්‍රව්‍ය සමග විදෙස් කතක් ගුවන්තොටේ දී අත්අඩංගුවට",
    "href": "/articles/8E54anfkG90nIbC3jd9n",
    "byline": "",
    "timestamp": "2 hours ago",
    "url": "https://www.aruna.lk/articles/8E54anfkG90nIbC3jd9n",
    "isoTimestamp": "2025-07-22T13:28:53+05:30",
    "baseUrl": "https://www.aruna.lk",
    "checkSum": "721a82d4602d39cb32453b84be894969629f86107e41ca7bb9eb6b92a18d5595"
  },
  {
    "title": "කාලගුණයෙන් රතු නිවේදනයක්",
    "href": "/articles/oa5Kp3oi4B22iG4SxNeG",
    "byline": "",
    "timestamp": "2 hours ago",
    "url": "https://www.aruna.lk/articles/oa5Kp3oi4B22iG4SxNeG",
    "isoTimestamp": "2025-07-22T13:28:53+05:30",
    "baseUrl": "https://www.aruna.lk",
    "checkSum": "7d6c1e03e68a436a033c8e1f5dabd0a0caf9d8a3ff1eceb6a6af5cf84eec8d72"
  },
  {
    "title": "ඉන්දීය උප ජනපති ධුරයෙන් ඉවත් වෙයි",
    "href": "/articles/7E6pxQxniDbH37LWXO9c",
    "byline": "",
    "timestamp": "3 hours ago",
    "url": "https://www.aruna.lk/articles/7E6pxQxniDbH37LWXO9c",
    "isoTimestamp": "2025-07-22T13:27:53+05:30",
    "baseUrl": "https://www.aruna.lk",
    "checkSum": "f40b5ee12ddbdf3cd9ca2535a52ce8ea317cc23ea0ec904d914e48261a475c7a"
  },
  {
    "title": "ගැමි කතුන්ට ඉදිරියේදී පිරිමි හොයන්න අමාරු වෙයි",
    "href": "/articles/tmwcdvpTuLDIRxDM7W57",
    "byline": "",
    "timestamp": "3 hours ago",
    "url": "https://www.aruna.lk/articles/tmwcdvpTuLDIRxDM7W57",
    "isoTimestamp": "2025-07-22T13:27:53+05:30",
    "baseUrl": "https://www.aruna.lk",
    "checkSum": "98d256f37efac5d69a03fc9c72b25707bedf0684b26b4b82b499db8c7a54c22e"
  },
  {
    "title": "බංග්ලාදේශ ගුවන් අනතුරින් මිය ගිය පිරිස 27 දක්වා ඉහළට",
    "href": "/articles/d2Jd3rQA9f7s3pHuagZR",
    "byline": "",
    "timestamp": "3 hours ago",
    "url": "https://www.aruna.lk/articles/d2Jd3rQA9f7s3pHuagZR",
    "isoTimestamp": "2025-07-22T13:27:53+05:30",
    "baseUrl": "https://www.aruna.lk",
    "checkSum": "5e113326537027a0a6b0794c86d31082354eb125afd8c51332a06845c9e48bb5"
  },
  {
    "title": "හිටපු ජනාධිපතිවරුන්ට දෙන වරප්‍රසාද කපන පනත පාර්ලිමේන්තුවට",
    "href": "/articles/5osWDhlF1CMBiPw2eCLa",
    "byline": "",
    "timestamp": "30 minutes ago",
    "url": "https://www.aruna.lk/articles/5osWDhlF1CMBiPw2eCLa",
    "isoTimestamp": "2025-07-22T16:00:35+05:30",
    "baseUrl": "https://www.aruna.lk",
    "checkSum": "3f05059653673e334ff1e1e939076f63b05cd2603ef2329f5752c2242f6432ce"
  },
  {
    "title": "ශ්‍රී ලංකන් ගුවන්කරණ රක්ෂණ කොන්ත්‍රාත්තු පිරිනැමීමට අනුමැතිය",
    "href": "/articles/cLHROQ6b0OIlmbjgGMdX",
    "byline": "",
    "timestamp": "an hour ago",
    "url": "https://www.aruna.lk/articles/cLHROQ6b0OIlmbjgGMdX",
    "isoTimestamp": "2025-07-22T16:30:35+05:30",
    "baseUrl": "https://www.aruna.lk",
    "checkSum": "9621675296c7766cc7382d7c3c57f516199aafc300426b10a4757fa5aa5cbb56"
  },
  {
    "title": "උසස් ජාතික ඩිප්ලෝමා දෙකකට NVQ6 සහතිකය පිරිනැමීමට අනුමැතිය",
    "href": "/articles/GKe6GdqZlrvIwKsBniet",
    "byline": "",
    "timestamp": "an hour ago",
    "url": "https://www.aruna.lk/articles/GKe6GdqZlrvIwKsBniet",
    "isoTimestamp": "2025-07-22T16:30:35+05:30",
    "baseUrl": "https://www.aruna.lk",
    "checkSum": "e27a2f62cbf9768e47fce9fe97b2c7d1ddb7cfe7a8996f91e7698bf42e608d6b"
  },
  {
    "title": "AI සංවර්ධනයට සිංගප්පූරුවේ සහාය",
    "href": "/articles/YDoliBt3LuvDBei4Li4D",
    "byline": "",
    "timestamp": "an hour ago",
    "url": "https://www.aruna.lk/articles/YDoliBt3LuvDBei4Li4D",
    "isoTimestamp": "2025-07-22T16:30:35+05:30",
    "baseUrl": "https://www.aruna.lk",
    "checkSum": "720c2f4e5ae686e7020d12cfe6f6d09f64c779d6c84c5c9d150f966dec71c996"
  },
  {
    "title": "මනූෂ නානායක්කාරගේ  පෞද්ගලික ලේකම් අත්අඩංගුවට",
    "href": "/articles/8U9Q3TohkCmvScezTBGe",
    "byline": "",
    "timestamp": "2 hours ago",
    "url": "https://www.aruna.lk/articles/8U9Q3TohkCmvScezTBGe",
    "isoTimestamp": "2025-07-22T16:28:35+05:30",
    "baseUrl": "https://www.aruna.lk",
    "checkSum": "e0410ec3d6a2a8370cab21ea6e0987c4ec0760d71abaceae9111ee0bf1d22d22"
  },
  {
    "title": "නිට්ටඹුවේ ගින්නක් - දැඩි රථවාහන තදබදයක්",
    "href": "/articles/1wykJoxL0coGobGOqOmE",
    "byline": "",
    "timestamp": "2 hours ago",
    "url": "https://www.aruna.lk/articles/1wykJoxL0coGobGOqOmE",
    "isoTimestamp": "2025-07-22T16:28:35+05:30",
    "baseUrl": "https://www.aruna.lk",
    "checkSum": "8295804e248b1688a8aecd1eb20648e489ba3d06d97a851b725fba9c57aec175"
  },
  {
    "title": "E-8 වීසා කාණ්ඩය යටතේ ශ්‍රමිකයින් යැවීමට අවබෝධතා ගිවිසුමක්",
    "href": "/articles/G5NZJnbd6hmYcFwGntis",
    "byline": "",
    "timestamp": "3 hours ago",
    "url": "https://www.aruna.lk/articles/G5NZJnbd6hmYcFwGntis",
    "isoTimestamp": "2025-07-22T16:27:35+05:30",
    "baseUrl": "https://www.aruna.lk",
    "checkSum": "d25544b1d161f3a17805cb1da4f38cb9212ef2508a3099617a47705713951f87"
  }
]
